{"browsers":{"firefox":{"34":false},"chrome":{"47":false},"explorer":{"8":false,"9":true,"10":false,"11":true},"safari":{"6":true,"7":true},"iphone":{"6.1":true,"7.1":true,"8.0":false,"8.1":false},"ipad":{"6.1":true,"7.1":true,"8.0":false,"8.1":false},"android-browser":{"4.0":true,"4.1":true,"4.4":true}},"raw":[{"browser_short_version":"8.1","video_url":"https://saucelabs.com/jobs/e934086e49cc448ab90ed09820de4968/video.flv","creation_time":1453175478,"custom-data":null,"browser_version":"8.1.","owner":"fcore","id":"e934086e49cc448ab90ed09820de4968","record_screenshots":true,"record_video":true,"build":"03-service_103261744","passed":false,"public":"public","end_time":1453175766,"status":"complete","log_url":"https://saucelabs.com/jobs/e934086e49cc448ab90ed09820de4968/selenium-server.log","start_time":1453175670,"proxied":true,"modification_time":1453175766,"tags":["103261744","1a3b410f3a27688727d8465d12cb3bdfc95dde98","fluxex"],"name":"FluxEx browser test for example: 03-service_103261744","commands_not_successful":4,"consolidated_status":"failed","assigned_tunnel_id":"35055b2460004312968e16ba97f00652","error":null,"os":"Mac 10.10","breakpointed":null,"browser":"iphone"},{"browser_short_version":"6.1","video_url":"https://saucelabs.com/jobs/e1a3b280c4014c148b1ec6e5372a8baf/video.flv","creation_time":1453175478,"custom-data":null,"browser_version":"6.1.","owner":"fcore","id":"e1a3b280c4014c148b1ec6e5372a8baf","record_screenshots":true,"record_video":true,"build":"03-service_103261744","passed":true,"public":"public","end_time":1453175717,"status":"complete","log_url":"https://saucelabs.com/jobs/e1a3b280c4014c148b1ec6e5372a8baf/selenium-server.log","start_time":1453175670,"proxied":true,"modification_time":1453175717,"tags":["103261744","1a3b410f3a27688727d8465d12cb3bdfc95dde98","fluxex"],"name":"FluxEx browser test for example: 03-service_103261744","commands_not_successful":6,"consolidated_status":"passed","assigned_tunnel_id":"35055b2460004312968e16ba97f00652","error":null,"os":"Mac 10.8","breakpointed":null,"browser":"ipad"},{"browser_short_version":"8","video_url":"https://saucelabs.com/jobs/d0937766c20249098a2a5b49d48f46ea/video.flv","creation_time":1453175478,"custom-data":null,"browser_version":"8.0.7601.17514.","owner":"fcore","id":"d0937766c20249098a2a5b49d48f46ea","record_screenshots":true,"record_video":true,"build":"03-service_103261744","passed":false,"public":"public","end_time":1453175489,"status":"complete","log_url":"https://saucelabs.com/jobs/d0937766c20249098a2a5b49d48f46ea/selenium-server.log","start_time":1453175479,"proxied":true,"modification_time":1453175489,"tags":["103261744","1a3b410f3a27688727d8465d12cb3bdfc95dde98","fluxex"],"name":"FluxEx browser test for example: 03-service_103261744","commands_not_successful":2,"consolidated_status":"failed","assigned_tunnel_id":"35055b2460004312968e16ba97f00652","error":null,"os":"Windows 2008","breakpointed":null,"browser":"iexplore"},{"browser_short_version":"47","video_url":"https://saucelabs.com/jobs/7510687130ce47769fc33f9a4833dad4/video.flv","creation_time":1453175478,"custom-data":null,"browser_version":"47.0.2526.73","owner":"fcore","id":"7510687130ce47769fc33f9a4833dad4","record_screenshots":true,"record_video":true,"build":"03-service_103261744","passed":false,"public":"public","end_time":1453175484,"status":"complete","log_url":"https://saucelabs.com/jobs/7510687130ce47769fc33f9a4833dad4/selenium-server.log","start_time":1453175478,"proxied":true,"modification_time":1453175484,"tags":["103261744","1a3b410f3a27688727d8465d12cb3bdfc95dde98","fluxex"],"name":"FluxEx browser test for example: 03-service_103261744","commands_not_successful":1,"consolidated_status":"failed","assigned_tunnel_id":"35055b2460004312968e16ba97f00652","error":null,"os":"Linux","breakpointed":null,"browser":"googlechrome"},{"browser_short_version":"6.1","video_url":"https://saucelabs.com/jobs/2a715a45ebbc4ebbb7665410ef9756a7/video.flv","creation_time":1453175478,"custom-data":null,"browser_version":"6.1.","owner":"fcore","id":"2a715a45ebbc4ebbb7665410ef9756a7","record_screenshots":true,"record_video":true,"build":"03-service_103261744","passed":true,"public":"public","end_time":1453175704,"status":"complete","log_url":"https://saucelabs.com/jobs/2a715a45ebbc4ebbb7665410ef9756a7/selenium-server.log","start_time":1453175670,"proxied":true,"modification_time":1453175704,"tags":["103261744","1a3b410f3a27688727d8465d12cb3bdfc95dde98","fluxex"],"name":"FluxEx browser test for example: 03-service_103261744","commands_not_successful":6,"consolidated_status":"passed","assigned_tunnel_id":"35055b2460004312968e16ba97f00652","error":null,"os":"Mac 10.8","breakpointed":null,"browser":"iphone"},{"browser_short_version":"11","video_url":"https://saucelabs.com/jobs/de4bfd957e9044d3aa9d5ed03cc75673/video.flv","creation_time":1453175477,"custom-data":null,"browser_version":"11.0.9600.17801.","owner":"fcore","id":"de4bfd957e9044d3aa9d5ed03cc75673","record_screenshots":true,"record_video":true,"build":"03-service_103261744","passed":true,"public":"public","end_time":1453175492,"status":"complete","log_url":"https://saucelabs.com/jobs/de4bfd957e9044d3aa9d5ed03cc75673/selenium-server.log","start_time":1453175478,"proxied":true,"modification_time":1453175493,"tags":["103261744","1a3b410f3a27688727d8465d12cb3bdfc95dde98","fluxex"],"name":"FluxEx browser test for example: 03-service_103261744","commands_not_successful":2,"consolidated_status":"passed","assigned_tunnel_id":"35055b2460004312968e16ba97f00652","error":null,"os":"Windows 2012 R2","breakpointed":null,"browser":"iexplore"},{"browser_short_version":"8.1","video_url":"https://saucelabs.com/jobs/d3bd39720b7b4609a3163224807d7147/video.flv","creation_time":1453175477,"custom-data":null,"browser_version":"8.1.","owner":"fcore","id":"d3bd39720b7b4609a3163224807d7147","record_screenshots":true,"record_video":true,"build":"03-service_103261744","passed":false,"public":"public","end_time":null,"status":"in progress","log_url":"https://saucelabs.com/jobs/d3bd39720b7b4609a3163224807d7147/selenium-server.log","start_time":1453175669,"proxied":true,"modification_time":1453175832,"tags":["103261744","1a3b410f3a27688727d8465d12cb3bdfc95dde98","fluxex"],"name":"FluxEx browser test for example: 03-service_103261744","commands_not_successful":0,"consolidated_status":"failed","assigned_tunnel_id":"35055b2460004312968e16ba97f00652","error":null,"os":"Mac 10.10","breakpointed":null,"browser":"ipad"},{"browser_short_version":"7.1","video_url":"https://saucelabs.com/jobs/cc354d0430104c98a851cda6ea8bdecf/video.flv","creation_time":1453175477,"custom-data":null,"browser_version":"7.1.","owner":"fcore","id":"cc354d0430104c98a851cda6ea8bdecf","record_screenshots":true,"record_video":true,"build":"03-service_103261744","passed":true,"public":"public","end_time":1453175783,"status":"complete","log_url":"https://saucelabs.com/jobs/cc354d0430104c98a851cda6ea8bdecf/selenium-server.log","start_time":1453175670,"proxied":true,"modification_time":1453175783,"tags":["103261744","1a3b410f3a27688727d8465d12cb3bdfc95dde98","fluxex"],"name":"FluxEx browser test for example: 03-service_103261744","commands_not_successful":5,"consolidated_status":"passed","assigned_tunnel_id":"35055b2460004312968e16ba97f00652","error":null,"os":"Mac 10.9","breakpointed":null,"browser":"iphone"},{"browser_short_version":"8.0","video_url":"https://saucelabs.com/jobs/bd94590d5eee452a9c3d9edb59a03148/video.flv","creation_time":1453175477,"custom-data":null,"browser_version":"8.0.","owner":"fcore","id":"bd94590d5eee452a9c3d9edb59a03148","record_screenshots":true,"record_video":true,"build":"03-service_103261744","passed":false,"public":"public","end_time":1453175751,"status":"complete","log_url":"https://saucelabs.com/jobs/bd94590d5eee452a9c3d9edb59a03148/selenium-server.log","start_time":1453175669,"proxied":true,"modification_time":1453175752,"tags":["103261744","1a3b410f3a27688727d8465d12cb3bdfc95dde98","fluxex"],"name":"FluxEx browser test for example: 03-service_103261744","commands_not_successful":4,"consolidated_status":"failed","assigned_tunnel_id":"35055b2460004312968e16ba97f00652","error":null,"os":"Mac 10.10","breakpointed":null,"browser":"ipad"},{"browser_short_version":"8.0","video_url":"https://saucelabs.com/jobs/b4c9501126184ed2bd2179715d9c8964/video.flv","creation_time":1453175477,"custom-data":null,"browser_version":"8.0.","owner":"fcore","id":"b4c9501126184ed2bd2179715d9c8964","record_screenshots":true,"record_video":true,"build":"03-service_103261744","passed":false,"public":"public","end_time":1453175760,"status":"complete","log_url":"https://saucelabs.com/jobs/b4c9501126184ed2bd2179715d9c8964/selenium-server.log","start_time":1453175670,"proxied":true,"modification_time":1453175760,"tags":["103261744","1a3b410f3a27688727d8465d12cb3bdfc95dde98","fluxex"],"name":"FluxEx browser test for example: 03-service_103261744","commands_not_successful":4,"consolidated_status":"failed","assigned_tunnel_id":"35055b2460004312968e16ba97f00652","error":null,"os":"Mac 10.10","breakpointed":null,"browser":"iphone"},{"browser_short_version":"10","video_url":"https://saucelabs.com/jobs/b19a95993cec4003b636e4a6f1c4ff42/video.flv","creation_time":1453175477,"custom-data":null,"browser_version":"10.0.9200.16580.","owner":"fcore","id":"b19a95993cec4003b636e4a6f1c4ff42","record_screenshots":true,"record_video":true,"build":"03-service_103261744","passed":false,"public":"public","end_time":1453175489,"status":"complete","log_url":"https://saucelabs.com/jobs/b19a95993cec4003b636e4a6f1c4ff42/selenium-server.log","start_time":1453175478,"proxied":true,"modification_time":1453175489,"tags":["103261744","1a3b410f3a27688727d8465d12cb3bdfc95dde98","fluxex"],"name":"FluxEx browser test for example: 03-service_103261744","commands_not_successful":2,"consolidated_status":"failed","assigned_tunnel_id":"35055b2460004312968e16ba97f00652","error":null,"os":"Windows 2012","breakpointed":null,"browser":"iexplore"},{"browser_short_version":"7.1","video_url":"https://saucelabs.com/jobs/9ca8676a640843be9e03e0c8dbd509e3/video.flv","creation_time":1453175477,"custom-data":null,"browser_version":"7.1.","owner":"fcore","id":"9ca8676a640843be9e03e0c8dbd509e3","record_screenshots":true,"record_video":true,"build":"03-service_103261744","passed":true,"public":"public","end_time":1453175738,"status":"complete","log_url":"https://saucelabs.com/jobs/9ca8676a640843be9e03e0c8dbd509e3/selenium-server.log","start_time":1453175670,"proxied":true,"modification_time":1453175739,"tags":["103261744","1a3b410f3a27688727d8465d12cb3bdfc95dde98","fluxex"],"name":"FluxEx browser test for example: 03-service_103261744","commands_not_successful":5,"consolidated_status":"passed","assigned_tunnel_id":"35055b2460004312968e16ba97f00652","error":null,"os":"Mac 10.9","breakpointed":null,"browser":"ipad"},{"browser_short_version":"4.1","video_url":"https://saucelabs.com/jobs/9286da6cf9234d6fbcbe489086dbd386/video.flv","creation_time":1453175477,"custom-data":null,"browser_version":"4.1.","owner":"fcore","id":"9286da6cf9234d6fbcbe489086dbd386","record_screenshots":true,"record_video":true,"build":"03-service_103261744","passed":true,"public":"public","end_time":1453175520,"status":"complete","log_url":"https://saucelabs.com/jobs/9286da6cf9234d6fbcbe489086dbd386/selenium-server.log","start_time":1453175478,"proxied":true,"modification_time":1453175520,"tags":["103261744","1a3b410f3a27688727d8465d12cb3bdfc95dde98","fluxex"],"name":"FluxEx browser test for example: 03-service_103261744","commands_not_successful":4,"consolidated_status":"passed","assigned_tunnel_id":"35055b2460004312968e16ba97f00652","error":null,"os":"Linux","breakpointed":null,"browser":"android"},{"browser_short_version":"7","video_url":"https://saucelabs.com/jobs/8b7db88fbe7b4f1eba07fc7983670eb0/video.flv","creation_time":1453175477,"custom-data":null,"browser_version":"7.0.","owner":"fcore","id":"8b7db88fbe7b4f1eba07fc7983670eb0","record_screenshots":true,"record_video":true,"build":"03-service_103261744","passed":true,"public":"public","end_time":1453175701,"status":"complete","log_url":"https://saucelabs.com/jobs/8b7db88fbe7b4f1eba07fc7983670eb0/selenium-server.log","start_time":1453175670,"proxied":true,"modification_time":1453175701,"tags":["103261744","1a3b410f3a27688727d8465d12cb3bdfc95dde98","fluxex"],"name":"FluxEx browser test for example: 03-service_103261744","commands_not_successful":2,"consolidated_status":"passed","assigned_tunnel_id":"35055b2460004312968e16ba97f00652","error":null,"os":"Mac 10.9","breakpointed":null,"browser":"safari"},{"browser_short_version":"9","video_url":"https://saucelabs.com/jobs/71c7fbcab3ea4b11aba2a1f80516e028/video.flv","creation_time":1453175477,"custom-data":null,"browser_version":"9.0.8112.16421.","owner":"fcore","id":"71c7fbcab3ea4b11aba2a1f80516e028","record_screenshots":true,"record_video":true,"build":"03-service_103261744","passed":true,"public":"public","end_time":1453175492,"status":"complete","log_url":"https://saucelabs.com/jobs/71c7fbcab3ea4b11aba2a1f80516e028/selenium-server.log","start_time":1453175478,"proxied":true,"modification_time":1453175493,"tags":["103261744","1a3b410f3a27688727d8465d12cb3bdfc95dde98","fluxex"],"name":"FluxEx browser test for example: 03-service_103261744","commands_not_successful":2,"consolidated_status":"passed","assigned_tunnel_id":"35055b2460004312968e16ba97f00652","error":null,"os":"Windows 2008","breakpointed":null,"browser":"iexplore"},{"browser_short_version":"34","video_url":"https://saucelabs.com/jobs/58e8f460a9b44f9d920032f793100caf/video.flv","creation_time":1453175477,"custom-data":null,"browser_version":"34.0.","owner":"fcore","id":"58e8f460a9b44f9d920032f793100caf","record_screenshots":true,"record_video":true,"build":"03-service_103261744","passed":false,"public":"public","end_time":1453175486,"status":"complete","log_url":"https://saucelabs.com/jobs/58e8f460a9b44f9d920032f793100caf/selenium-server.log","start_time":1453175477,"proxied":true,"modification_time":1453175486,"tags":["103261744","1a3b410f3a27688727d8465d12cb3bdfc95dde98","fluxex"],"name":"FluxEx browser test for example: 03-service_103261744","commands_not_successful":1,"consolidated_status":"failed","assigned_tunnel_id":"35055b2460004312968e16ba97f00652","error":null,"os":"Linux","breakpointed":null,"browser":"firefox"},{"browser_short_version":"4.4","video_url":"https://saucelabs.com/jobs/551320625b1a48e1aa3f6a9be9843169/video.flv","creation_time":1453175477,"custom-data":null,"browser_version":"4.4.","owner":"fcore","id":"551320625b1a48e1aa3f6a9be9843169","record_screenshots":true,"record_video":true,"build":"03-service_103261744","passed":true,"public":"public","end_time":1453175532,"status":"complete","log_url":"https://saucelabs.com/jobs/551320625b1a48e1aa3f6a9be9843169/selenium-server.log","start_time":1453175478,"proxied":true,"modification_time":1453175532,"tags":["103261744","1a3b410f3a27688727d8465d12cb3bdfc95dde98","fluxex"],"name":"FluxEx browser test for example: 03-service_103261744","commands_not_successful":4,"consolidated_status":"passed","assigned_tunnel_id":"35055b2460004312968e16ba97f00652","error":null,"os":"Linux","breakpointed":null,"browser":"android"},{"browser_short_version":"4.0","video_url":"https://saucelabs.com/jobs/2356ecbcc0af4ee4971ed51c5cffd3b2/video.flv","creation_time":1453175477,"custom-data":null,"browser_version":"4.0.4.","owner":"fcore","id":"2356ecbcc0af4ee4971ed51c5cffd3b2","record_screenshots":true,"record_video":true,"build":"03-service_103261744","passed":true,"public":"public","end_time":1453175522,"status":"complete","log_url":"https://saucelabs.com/jobs/2356ecbcc0af4ee4971ed51c5cffd3b2/selenium-server.log","start_time":1453175478,"proxied":true,"modification_time":1453175523,"tags":["103261744","1a3b410f3a27688727d8465d12cb3bdfc95dde98","fluxex"],"name":"FluxEx browser test for example: 03-service_103261744","commands_not_successful":4,"consolidated_status":"passed","assigned_tunnel_id":"35055b2460004312968e16ba97f00652","error":null,"os":"Linux","breakpointed":null,"browser":"android"},{"browser_short_version":"6","video_url":"https://saucelabs.com/jobs/12ed2790f79b4176b67cfa1a0cd798c2/video.flv","creation_time":1453175477,"custom-data":null,"browser_version":"6.0.4.","owner":"fcore","id":"12ed2790f79b4176b67cfa1a0cd798c2","record_screenshots":true,"record_video":true,"build":"03-service_103261744","passed":true,"public":"public","end_time":1453175691,"status":"complete","log_url":"https://saucelabs.com/jobs/12ed2790f79b4176b67cfa1a0cd798c2/selenium-server.log","start_time":1453175670,"proxied":true,"modification_time":1453175691,"tags":["103261744","1a3b410f3a27688727d8465d12cb3bdfc95dde98","fluxex"],"name":"FluxEx browser test for example: 03-service_103261744","commands_not_successful":2,"consolidated_status":"passed","assigned_tunnel_id":"35055b2460004312968e16ba97f00652","error":null,"os":"Mac 10.8","breakpointed":null,"browser":"safari"},{"browser_short_version":"6.1","video_url":"https://saucelabs.com/jobs/fb4b43f4f8e7495580fcf8e3d1acd54a/video.flv","creation_time":1453175275,"custom-data":null,"browser_version":"6.1.","owner":"fcore","id":"fb4b43f4f8e7495580fcf8e3d1acd54a","record_screenshots":true,"record_video":true,"build":"02-routing_103261744","passed":false,"public":"public","end_time":1453175322,"status":"complete","log_url":"https://saucelabs.com/jobs/fb4b43f4f8e7495580fcf8e3d1acd54a/selenium-server.log","start_time":1453175276,"proxied":true,"modification_time":1453175322,"tags":["103261744","1a3b410f3a27688727d8465d12cb3bdfc95dde98","fluxex"],"name":"FluxEx browser test for example: 02-routing_103261744","commands_not_successful":14,"consolidated_status":"failed","assigned_tunnel_id":"35055b2460004312968e16ba97f00652","error":null,"os":"Mac 10.8","breakpointed":null,"browser":"ipad"},{"browser_short_version":"8.1","video_url":"https://saucelabs.com/jobs/ef4bd08ba3934f468a994bb43aaafd4a/video.flv","creation_time":1453175275,"custom-data":null,"browser_version":"8.1.","owner":"fcore","id":"ef4bd08ba3934f468a994bb43aaafd4a","record_screenshots":true,"record_video":true,"build":"02-routing_103261744","passed":false,"public":"public","end_time":1453175430,"status":"complete","log_url":"https://saucelabs.com/jobs/ef4bd08ba3934f468a994bb43aaafd4a/selenium-server.log","start_time":1453175276,"proxied":true,"modification_time":1453175430,"tags":["103261744","1a3b410f3a27688727d8465d12cb3bdfc95dde98","fluxex"],"name":"FluxEx browser test for example: 02-routing_103261744","commands_not_successful":288,"consolidated_status":"failed","assigned_tunnel_id":"35055b2460004312968e16ba97f00652","error":null,"os":"Mac 10.10","breakpointed":null,"browser":"iphone"},{"browser_short_version":"8","video_url":"https://saucelabs.com/jobs/ed6d118c7a3346e7a035adf2fde0ce41/video.flv","creation_time":1453175275,"custom-data":null,"browser_version":"8.0.7601.17514.","owner":"fcore","id":"ed6d118c7a3346e7a035adf2fde0ce41","record_screenshots":true,"record_video":true,"build":"02-routing_103261744","passed":false,"public":"public","end_time":1453175291,"status":"complete","log_url":"https://saucelabs.com/jobs/ed6d118c7a3346e7a035adf2fde0ce41/selenium-server.log","start_time":1453175276,"proxied":true,"modification_time":1453175291,"tags":["103261744","1a3b410f3a27688727d8465d12cb3bdfc95dde98","fluxex"],"name":"FluxEx browser test for example: 02-routing_103261744","commands_not_successful":5,"consolidated_status":"failed","assigned_tunnel_id":"35055b2460004312968e16ba97f00652","error":null,"os":"Windows 2008","breakpointed":null,"browser":"iexplore"},{"browser_short_version":"7.1","video_url":"https://saucelabs.com/jobs/e4529796a8614713880ba2bce62f67da/video.flv","creation_time":1453175275,"custom-data":null,"browser_version":"7.1.","owner":"fcore","id":"e4529796a8614713880ba2bce62f67da","record_screenshots":true,"record_video":true,"build":"02-routing_103261744","passed":false,"public":"public","end_time":1453175404,"status":"complete","log_url":"https://saucelabs.com/jobs/e4529796a8614713880ba2bce62f67da/selenium-server.log","start_time":1453175276,"proxied":true,"modification_time":1453175404,"tags":["103261744","1a3b410f3a27688727d8465d12cb3bdfc95dde98","fluxex"],"name":"FluxEx browser test for example: 02-routing_103261744","commands_not_successful":12,"consolidated_status":"failed","assigned_tunnel_id":"35055b2460004312968e16ba97f00652","error":null,"os":"Mac 10.9","breakpointed":null,"browser":"iphone"},{"browser_short_version":"7","video_url":"https://saucelabs.com/jobs/e3059a020d3e49578e5e76cbd004abde/video.flv","creation_time":1453175275,"custom-data":null,"browser_version":"7.0.","owner":"fcore","id":"e3059a020d3e49578e5e76cbd004abde","record_screenshots":true,"record_video":true,"build":"02-routing_103261744","passed":false,"public":"public","end_time":1453175298,"status":"complete","log_url":"https://saucelabs.com/jobs/e3059a020d3e49578e5e76cbd004abde/selenium-server.log","start_time":1453175276,"proxied":true,"modification_time":1453175298,"tags":["103261744","1a3b410f3a27688727d8465d12cb3bdfc95dde98","fluxex"],"name":"FluxEx browser test for example: 02-routing_103261744","commands_not_successful":9,"consolidated_status":"failed","assigned_tunnel_id":"35055b2460004312968e16ba97f00652","error":null,"os":"Mac 10.9","breakpointed":null,"browser":"safari"},{"browser_short_version":"8.0","video_url":"https://saucelabs.com/jobs/d77c5e4a8b0e4b5187ee77c79e65cc13/video.flv","creation_time":1453175275,"custom-data":null,"browser_version":"8.0.","owner":"fcore","id":"d77c5e4a8b0e4b5187ee77c79e65cc13","record_screenshots":true,"record_video":true,"build":"02-routing_103261744","passed":false,"public":"public","end_time":1453175430,"status":"complete","log_url":"https://saucelabs.com/jobs/d77c5e4a8b0e4b5187ee77c79e65cc13/selenium-server.log","start_time":1453175276,"proxied":true,"modification_time":1453175430,"tags":["103261744","1a3b410f3a27688727d8465d12cb3bdfc95dde98","fluxex"],"name":"FluxEx browser test for example: 02-routing_103261744","commands_not_successful":291,"consolidated_status":"failed","assigned_tunnel_id":"35055b2460004312968e16ba97f00652","error":null,"os":"Mac 10.10","breakpointed":null,"browser":"iphone"},{"browser_short_version":"47","video_url":"https://saucelabs.com/jobs/b283fa27f8a7412cb95197f61b5bcbd0/video.flv","creation_time":1453175275,"custom-data":null,"browser_version":"47.0.2526.73","owner":"fcore","id":"b283fa27f8a7412cb95197f61b5bcbd0","record_screenshots":true,"record_video":true,"build":"02-routing_103261744","passed":false,"public":"public","end_time":1453175349,"status":"complete","log_url":"https://saucelabs.com/jobs/b283fa27f8a7412cb95197f61b5bcbd0/selenium-server.log","start_time":1453175275,"proxied":true,"modification_time":1453175349,"tags":["103261744","1a3b410f3a27688727d8465d12cb3bdfc95dde98","fluxex"],"name":"FluxEx browser test for example: 02-routing_103261744","commands_not_successful":312,"consolidated_status":"failed","assigned_tunnel_id":"35055b2460004312968e16ba97f00652","error":null,"os":"Linux","breakpointed":null,"browser":"googlechrome"},{"browser_short_version":"9","video_url":"https://saucelabs.com/jobs/8a22d8379c0443599d263225facf584d/video.flv","creation_time":1453175275,"custom-data":null,"browser_version":"9.0.8112.16421.","owner":"fcore","id":"8a22d8379c0443599d263225facf584d","record_screenshots":true,"record_video":true,"build":"02-routing_103261744","passed":false,"public":"public","end_time":1453175294,"status":"complete","log_url":"https://saucelabs.com/jobs/8a22d8379c0443599d263225facf584d/selenium-server.log","start_time":1453175276,"proxied":true,"modification_time":1453175294,"tags":["103261744","1a3b410f3a27688727d8465d12cb3bdfc95dde98","fluxex"],"name":"FluxEx browser test for example: 02-routing_103261744","commands_not_successful":5,"consolidated_status":"failed","assigned_tunnel_id":"35055b2460004312968e16ba97f00652","error":null,"os":"Windows 2008","breakpointed":null,"browser":"iexplore"},{"browser_short_version":"6","video_url":"https://saucelabs.com/jobs/54dee7dcc9b347c098477c67c034dd33/video.flv","creation_time":1453175275,"custom-data":null,"browser_version":"6.0.4.","owner":"fcore","id":"54dee7dcc9b347c098477c67c034dd33","record_screenshots":true,"record_video":true,"build":"02-routing_103261744","passed":false,"public":"public","end_time":1453175300,"status":"complete","log_url":"https://saucelabs.com/jobs/54dee7dcc9b347c098477c67c034dd33/selenium-server.log","start_time":1453175275,"proxied":true,"modification_time":1453175300,"tags":["103261744","1a3b410f3a27688727d8465d12cb3bdfc95dde98","fluxex"],"name":"FluxEx browser test for example: 02-routing_103261744","commands_not_successful":9,"consolidated_status":"failed","assigned_tunnel_id":"35055b2460004312968e16ba97f00652","error":null,"os":"Mac 10.8","breakpointed":null,"browser":"safari"},{"browser_short_version":"6.1","video_url":"https://saucelabs.com/jobs/53a4a2be24e54ed3b3dc5c09e3ecc9da/video.flv","creation_time":1453175275,"custom-data":null,"browser_version":"6.1.","owner":"fcore","id":"53a4a2be24e54ed3b3dc5c09e3ecc9da","record_screenshots":true,"record_video":true,"build":"02-routing_103261744","passed":false,"public":"public","end_time":1453175322,"status":"complete","log_url":"https://saucelabs.com/jobs/53a4a2be24e54ed3b3dc5c09e3ecc9da/selenium-server.log","start_time":1453175276,"proxied":true,"modification_time":1453175322,"tags":["103261744","1a3b410f3a27688727d8465d12cb3bdfc95dde98","fluxex"],"name":"FluxEx browser test for example: 02-routing_103261744","commands_not_successful":14,"consolidated_status":"failed","assigned_tunnel_id":"35055b2460004312968e16ba97f00652","error":null,"os":"Mac 10.8","breakpointed":null,"browser":"iphone"},{"browser_short_version":"11","video_url":"https://saucelabs.com/jobs/49a65ba43cbb4ac8b102e2d84f8b818a/video.flv","creation_time":1453175275,"custom-data":null,"browser_version":"11.0.9600.17801.","owner":"fcore","id":"49a65ba43cbb4ac8b102e2d84f8b818a","record_screenshots":true,"record_video":true,"build":"02-routing_103261744","passed":false,"public":"public","end_time":1453175292,"status":"complete","log_url":"https://saucelabs.com/jobs/49a65ba43cbb4ac8b102e2d84f8b818a/selenium-server.log","start_time":1453175276,"proxied":true,"modification_time":1453175293,"tags":["103261744","1a3b410f3a27688727d8465d12cb3bdfc95dde98","fluxex"],"name":"FluxEx browser test for example: 02-routing_103261744","commands_not_successful":9,"consolidated_status":"failed","assigned_tunnel_id":"35055b2460004312968e16ba97f00652","error":null,"os":"Windows 2012 R2","breakpointed":null,"browser":"iexplore"},{"browser_short_version":"8.1","video_url":"https://saucelabs.com/jobs/45f56a71c30c4acab1fca4c711ec5cce/video.flv","creation_time":1453175275,"custom-data":null,"browser_version":"8.1.","owner":"fcore","id":"45f56a71c30c4acab1fca4c711ec5cce","record_screenshots":true,"record_video":true,"build":"02-routing_103261744","passed":false,"public":"public","end_time":1453175429,"status":"complete","log_url":"https://saucelabs.com/jobs/45f56a71c30c4acab1fca4c711ec5cce/selenium-server.log","start_time":1453175276,"proxied":true,"modification_time":1453175429,"tags":["103261744","1a3b410f3a27688727d8465d12cb3bdfc95dde98","fluxex"],"name":"FluxEx browser test for example: 02-routing_103261744","commands_not_successful":287,"consolidated_status":"failed","assigned_tunnel_id":"35055b2460004312968e16ba97f00652","error":null,"os":"Mac 10.10","breakpointed":null,"browser":"ipad"},{"browser_short_version":"8.0","video_url":"https://saucelabs.com/jobs/44f6e76e740b4939aba85ba867a7e10f/video.flv","creation_time":1453175275,"custom-data":null,"browser_version":"8.0.","owner":"fcore","id":"44f6e76e740b4939aba85ba867a7e10f","record_screenshots":true,"record_video":true,"build":"02-routing_103261744","passed":false,"public":"public","end_time":1453175420,"status":"complete","log_url":"https://saucelabs.com/jobs/44f6e76e740b4939aba85ba867a7e10f/selenium-server.log","start_time":1453175276,"proxied":true,"modification_time":1453175421,"tags":["103261744","1a3b410f3a27688727d8465d12cb3bdfc95dde98","fluxex"],"name":"FluxEx browser test for example: 02-routing_103261744","commands_not_successful":282,"consolidated_status":"failed","assigned_tunnel_id":"35055b2460004312968e16ba97f00652","error":null,"os":"Mac 10.10","breakpointed":null,"browser":"ipad"},{"browser_short_version":"7.1","video_url":"https://saucelabs.com/jobs/2cd4663369844c0f9061342099e2ef5b/video.flv","creation_time":1453175275,"custom-data":null,"browser_version":"7.1.","owner":"fcore","id":"2cd4663369844c0f9061342099e2ef5b","record_screenshots":true,"record_video":true,"build":"02-routing_103261744","passed":false,"public":"public","end_time":1453175347,"status":"complete","log_url":"https://saucelabs.com/jobs/2cd4663369844c0f9061342099e2ef5b/selenium-server.log","start_time":1453175276,"proxied":true,"modification_time":1453175347,"tags":["103261744","1a3b410f3a27688727d8465d12cb3bdfc95dde98","fluxex"],"name":"FluxEx browser test for example: 02-routing_103261744","commands_not_successful":12,"consolidated_status":"failed","assigned_tunnel_id":"35055b2460004312968e16ba97f00652","error":null,"os":"Mac 10.9","breakpointed":null,"browser":"ipad"},{"browser_short_version":"4.0","video_url":"https://saucelabs.com/jobs/2bf689b20cc54b719ff35a7b1aa6bc78/video.flv","creation_time":1453175275,"custom-data":null,"browser_version":"4.0.4.","owner":"fcore","id":"2bf689b20cc54b719ff35a7b1aa6bc78","record_screenshots":true,"record_video":true,"build":"02-routing_103261744","passed":false,"public":"public","end_time":1453175337,"status":"complete","log_url":"https://saucelabs.com/jobs/2bf689b20cc54b719ff35a7b1aa6bc78/selenium-server.log","start_time":1453175276,"proxied":true,"modification_time":1453175337,"tags":["103261744","1a3b410f3a27688727d8465d12cb3bdfc95dde98","fluxex"],"name":"FluxEx browser test for example: 02-routing_103261744","commands_not_successful":12,"consolidated_status":"failed","assigned_tunnel_id":"35055b2460004312968e16ba97f00652","error":null,"os":"Linux","breakpointed":null,"browser":"android"},{"browser_short_version":"4.4","video_url":"https://saucelabs.com/jobs/2876afcf57d942899db100ad48699b5d/video.flv","creation_time":1453175275,"custom-data":null,"browser_version":"4.4.","owner":"fcore","id":"2876afcf57d942899db100ad48699b5d","record_screenshots":true,"record_video":true,"build":"02-routing_103261744","passed":false,"public":"public","end_time":1453175355,"status":"complete","log_url":"https://saucelabs.com/jobs/2876afcf57d942899db100ad48699b5d/selenium-server.log","start_time":1453175276,"proxied":true,"modification_time":1453175355,"tags":["103261744","1a3b410f3a27688727d8465d12cb3bdfc95dde98","fluxex"],"name":"FluxEx browser test for example: 02-routing_103261744","commands_not_successful":12,"consolidated_status":"failed","assigned_tunnel_id":"35055b2460004312968e16ba97f00652","error":null,"os":"Linux","breakpointed":null,"browser":"android"},{"browser_short_version":"4.1","video_url":"https://saucelabs.com/jobs/19828d4e93a74c549348177ff776a559/video.flv","creation_time":1453175275,"custom-data":null,"browser_version":"4.1.","owner":"fcore","id":"19828d4e93a74c549348177ff776a559","record_screenshots":true,"record_video":true,"build":"02-routing_103261744","passed":false,"public":"public","end_time":1453175338,"status":"complete","log_url":"https://saucelabs.com/jobs/19828d4e93a74c549348177ff776a559/selenium-server.log","start_time":1453175276,"proxied":true,"modification_time":1453175338,"tags":["103261744","1a3b410f3a27688727d8465d12cb3bdfc95dde98","fluxex"],"name":"FluxEx browser test for example: 02-routing_103261744","commands_not_successful":12,"consolidated_status":"failed","assigned_tunnel_id":"35055b2460004312968e16ba97f00652","error":null,"os":"Linux","breakpointed":null,"browser":"android"},{"browser_short_version":"10","video_url":"https://saucelabs.com/jobs/155c05e0070a4b83b032290b0cff57a7/video.flv","creation_time":1453175275,"custom-data":null,"browser_version":"10.0.9200.16580.","owner":"fcore","id":"155c05e0070a4b83b032290b0cff57a7","record_screenshots":true,"record_video":true,"build":"02-routing_103261744","passed":false,"public":"public","end_time":1453175290,"status":"complete","log_url":"https://saucelabs.com/jobs/155c05e0070a4b83b032290b0cff57a7/selenium-server.log","start_time":1453175276,"proxied":true,"modification_time":1453175291,"tags":["103261744","1a3b410f3a27688727d8465d12cb3bdfc95dde98","fluxex"],"name":"FluxEx browser test for example: 02-routing_103261744","commands_not_successful":4,"consolidated_status":"failed","assigned_tunnel_id":"35055b2460004312968e16ba97f00652","error":null,"os":"Windows 2012","breakpointed":null,"browser":"iexplore"},{"browser_short_version":"34","video_url":"https://saucelabs.com/jobs/120baf0f3faf45429090ed39279b1044/video.flv","creation_time":1453175275,"custom-data":null,"browser_version":"34.0.","owner":"fcore","id":"120baf0f3faf45429090ed39279b1044","record_screenshots":true,"record_video":true,"build":"02-routing_103261744","passed":false,"public":"public","end_time":1453175296,"status":"complete","log_url":"https://saucelabs.com/jobs/120baf0f3faf45429090ed39279b1044/selenium-server.log","start_time":1453175275,"proxied":true,"modification_time":1453175297,"tags":["103261744","1a3b410f3a27688727d8465d12cb3bdfc95dde98","fluxex"],"name":"FluxEx browser test for example: 02-routing_103261744","commands_not_successful":9,"consolidated_status":"failed","assigned_tunnel_id":"35055b2460004312968e16ba97f00652","error":null,"os":"Linux","breakpointed":null,"browser":"firefox"},{"browser_short_version":"7","video_url":"https://saucelabs.com/jobs/f9b194c07d6d4e3dbdfdc5002c3edd09/video.flv","creation_time":1453175044,"custom-data":null,"browser_version":"7.0.","owner":"fcore","id":"f9b194c07d6d4e3dbdfdc5002c3edd09","record_screenshots":true,"record_video":true,"build":"01-history-api_103261744","passed":true,"public":"public","end_time":1453175070,"status":"complete","log_url":"https://saucelabs.com/jobs/f9b194c07d6d4e3dbdfdc5002c3edd09/selenium-server.log","start_time":1453175044,"proxied":true,"modification_time":1453175070,"tags":["103261744","1a3b410f3a27688727d8465d12cb3bdfc95dde98","fluxex"],"name":"FluxEx browser test for example: 01-history-api_103261744","commands_not_successful":4,"consolidated_status":"passed","assigned_tunnel_id":"35055b2460004312968e16ba97f00652","error":null,"os":"Mac 10.9","breakpointed":null,"browser":"safari"},{"browser_short_version":"7.1","video_url":"https://saucelabs.com/jobs/f4d36e5db1b045bab80da6408d4b5d54/video.flv","creation_time":1453175044,"custom-data":null,"browser_version":"7.1.","owner":"fcore","id":"f4d36e5db1b045bab80da6408d4b5d54","record_screenshots":true,"record_video":true,"build":"01-history-api_103261744","passed":true,"public":"public","end_time":1453175119,"status":"complete","log_url":"https://saucelabs.com/jobs/f4d36e5db1b045bab80da6408d4b5d54/selenium-server.log","start_time":1453175045,"proxied":true,"modification_time":1453175119,"tags":["103261744","1a3b410f3a27688727d8465d12cb3bdfc95dde98","fluxex"],"name":"FluxEx browser test for example: 01-history-api_103261744","commands_not_successful":8,"consolidated_status":"passed","assigned_tunnel_id":"35055b2460004312968e16ba97f00652","error":null,"os":"Mac 10.9","breakpointed":null,"browser":"iphone"},{"browser_short_version":"9","video_url":"https://saucelabs.com/jobs/e6eb18f48c4340c9a57c736da36358bf/video.flv","creation_time":1453175044,"custom-data":null,"browser_version":"9.0.8112.16421.","owner":"fcore","id":"e6eb18f48c4340c9a57c736da36358bf","record_screenshots":true,"record_video":true,"build":"01-history-api_103261744","passed":true,"public":"public","end_time":1453175065,"status":"complete","log_url":"https://saucelabs.com/jobs/e6eb18f48c4340c9a57c736da36358bf/selenium-server.log","start_time":1453175045,"proxied":true,"modification_time":1453175065,"tags":["103261744","1a3b410f3a27688727d8465d12cb3bdfc95dde98","fluxex"],"name":"FluxEx browser test for example: 01-history-api_103261744","commands_not_successful":4,"consolidated_status":"passed","assigned_tunnel_id":"35055b2460004312968e16ba97f00652","error":null,"os":"Windows 2008","breakpointed":null,"browser":"iexplore"},{"browser_short_version":"10","video_url":"https://saucelabs.com/jobs/cd2d08a497824b7db994e0a911091059/video.flv","creation_time":1453175044,"custom-data":null,"browser_version":"10.0.9200.16580.","owner":"fcore","id":"cd2d08a497824b7db994e0a911091059","record_screenshots":true,"record_video":true,"build":"01-history-api_103261744","passed":false,"public":"public","end_time":1453175056,"status":"complete","log_url":"https://saucelabs.com/jobs/cd2d08a497824b7db994e0a911091059/selenium-server.log","start_time":1453175045,"proxied":true,"modification_time":1453175057,"tags":["103261744","1a3b410f3a27688727d8465d12cb3bdfc95dde98","fluxex"],"name":"FluxEx browser test for example: 01-history-api_103261744","commands_not_successful":1,"consolidated_status":"failed","assigned_tunnel_id":"35055b2460004312968e16ba97f00652","error":null,"os":"Windows 2012","breakpointed":null,"browser":"iexplore"},{"browser_short_version":"4.0","video_url":"https://saucelabs.com/jobs/cac72c0327a143eb8095acfd854b7aad/video.flv","creation_time":1453175044,"custom-data":null,"browser_version":"4.0.4.","owner":"fcore","id":"cac72c0327a143eb8095acfd854b7aad","record_screenshots":true,"record_video":true,"build":"01-history-api_103261744","passed":true,"public":"public","end_time":1453175095,"status":"complete","log_url":"https://saucelabs.com/jobs/cac72c0327a143eb8095acfd854b7aad/selenium-server.log","start_time":1453175045,"proxied":true,"modification_time":1453175095,"tags":["103261744","1a3b410f3a27688727d8465d12cb3bdfc95dde98","fluxex"],"name":"FluxEx browser test for example: 01-history-api_103261744","commands_not_successful":8,"consolidated_status":"passed","assigned_tunnel_id":"35055b2460004312968e16ba97f00652","error":null,"os":"Linux","breakpointed":null,"browser":"android"},{"browser_short_version":"34","video_url":"https://saucelabs.com/jobs/c30713d0489c4cb3b9cdc406a51c9733/video.flv","creation_time":1453175044,"custom-data":null,"browser_version":"34.0.","owner":"fcore","id":"c30713d0489c4cb3b9cdc406a51c9733","record_screenshots":true,"record_video":true,"build":"01-history-api_103261744","passed":false,"public":"public","end_time":1453175055,"status":"complete","log_url":"https://saucelabs.com/jobs/c30713d0489c4cb3b9cdc406a51c9733/selenium-server.log","start_time":1453175044,"proxied":true,"modification_time":1453175056,"tags":["103261744","1a3b410f3a27688727d8465d12cb3bdfc95dde98","fluxex"],"name":"FluxEx browser test for example: 01-history-api_103261744","commands_not_successful":1,"consolidated_status":"failed","assigned_tunnel_id":"35055b2460004312968e16ba97f00652","error":null,"os":"Linux","breakpointed":null,"browser":"firefox"},{"browser_short_version":"7.1","video_url":"https://saucelabs.com/jobs/a24a555665ec454bb1970cfdcd12aed5/video.flv","creation_time":1453175044,"custom-data":null,"browser_version":"7.1.","owner":"fcore","id":"a24a555665ec454bb1970cfdcd12aed5","record_screenshots":true,"record_video":true,"build":"01-history-api_103261744","passed":true,"public":"public","end_time":1453175225,"status":"complete","log_url":"https://saucelabs.com/jobs/a24a555665ec454bb1970cfdcd12aed5/selenium-server.log","start_time":1453175045,"proxied":true,"modification_time":1453175226,"tags":["103261744","1a3b410f3a27688727d8465d12cb3bdfc95dde98","fluxex"],"name":"FluxEx browser test for example: 01-history-api_103261744","commands_not_successful":8,"consolidated_status":"passed","assigned_tunnel_id":"35055b2460004312968e16ba97f00652","error":null,"os":"Mac 10.9","breakpointed":null,"browser":"ipad"},{"browser_short_version":"6","video_url":"https://saucelabs.com/jobs/968d2ad6263e42c99e15600bfae0cf84/video.flv","creation_time":1453175044,"custom-data":null,"browser_version":"6.0.4.","owner":"fcore","id":"968d2ad6263e42c99e15600bfae0cf84","record_screenshots":true,"record_video":true,"build":"01-history-api_103261744","passed":true,"public":"public","end_time":1453175063,"status":"complete","log_url":"https://saucelabs.com/jobs/968d2ad6263e42c99e15600bfae0cf84/selenium-server.log","start_time":1453175044,"proxied":true,"modification_time":1453175063,"tags":["103261744","1a3b410f3a27688727d8465d12cb3bdfc95dde98","fluxex"],"name":"FluxEx browser test for example: 01-history-api_103261744","commands_not_successful":4,"consolidated_status":"passed","assigned_tunnel_id":"35055b2460004312968e16ba97f00652","error":null,"os":"Mac 10.8","breakpointed":null,"browser":"safari"},{"browser_short_version":"6.1","video_url":"https://saucelabs.com/jobs/9091c8ecf0334cdba2589580654bee8f/video.flv","creation_time":1453175044,"custom-data":null,"browser_version":"6.1.","owner":"fcore","id":"9091c8ecf0334cdba2589580654bee8f","record_screenshots":true,"record_video":true,"build":"01-history-api_103261744","passed":true,"public":"public","end_time":1453175086,"status":"complete","log_url":"https://saucelabs.com/jobs/9091c8ecf0334cdba2589580654bee8f/selenium-server.log","start_time":1453175045,"proxied":true,"modification_time":1453175086,"tags":["103261744","1a3b410f3a27688727d8465d12cb3bdfc95dde98","fluxex"],"name":"FluxEx browser test for example: 01-history-api_103261744","commands_not_successful":10,"consolidated_status":"passed","assigned_tunnel_id":"35055b2460004312968e16ba97f00652","error":null,"os":"Mac 10.8","breakpointed":null,"browser":"iphone"},{"browser_short_version":"8.0","video_url":"https://saucelabs.com/jobs/8c41e55727d24a619dbb814a0bac0ed4/video.flv","creation_time":1453175044,"custom-data":null,"browser_version":"8.0.","owner":"fcore","id":"8c41e55727d24a619dbb814a0bac0ed4","record_screenshots":true,"record_video":true,"build":"01-history-api_103261744","passed":true,"public":"public","end_time":1453175127,"status":"complete","log_url":"https://saucelabs.com/jobs/8c41e55727d24a619dbb814a0bac0ed4/selenium-server.log","start_time":1453175045,"proxied":true,"modification_time":1453175128,"tags":["103261744","1a3b410f3a27688727d8465d12cb3bdfc95dde98","fluxex"],"name":"FluxEx browser test for example: 01-history-api_103261744","commands_not_successful":8,"consolidated_status":"passed","assigned_tunnel_id":"35055b2460004312968e16ba97f00652","error":null,"os":"Mac 10.10","breakpointed":null,"browser":"iphone"},{"browser_short_version":"8","video_url":"https://saucelabs.com/jobs/7ca11d8f26a44104956cc92f5da8e426/video.flv","creation_time":1453175044,"custom-data":null,"browser_version":"8.0.7601.17514.","owner":"fcore","id":"7ca11d8f26a44104956cc92f5da8e426","record_screenshots":true,"record_video":true,"build":"01-history-api_103261744","passed":false,"public":"public","end_time":1453175057,"status":"complete","log_url":"https://saucelabs.com/jobs/7ca11d8f26a44104956cc92f5da8e426/selenium-server.log","start_time":1453175045,"proxied":true,"modification_time":1453175058,"tags":["103261744","1a3b410f3a27688727d8465d12cb3bdfc95dde98","fluxex"],"name":"FluxEx browser test for example: 01-history-api_103261744","commands_not_successful":1,"consolidated_status":"failed","assigned_tunnel_id":"35055b2460004312968e16ba97f00652","error":null,"os":"Windows 2008","breakpointed":null,"browser":"iexplore"},{"browser_short_version":"8.1","video_url":"https://saucelabs.com/jobs/78ec529dfaa44901aa78546e09c5f5e5/video.flv","creation_time":1453175044,"custom-data":null,"browser_version":"8.1.","owner":"fcore","id":"78ec529dfaa44901aa78546e09c5f5e5","record_screenshots":true,"record_video":true,"build":"01-history-api_103261744","passed":true,"public":"public","end_time":1453175146,"status":"complete","log_url":"https://saucelabs.com/jobs/78ec529dfaa44901aa78546e09c5f5e5/selenium-server.log","start_time":1453175045,"proxied":true,"modification_time":1453175146,"tags":["103261744","1a3b410f3a27688727d8465d12cb3bdfc95dde98","fluxex"],"name":"FluxEx browser test for example: 01-history-api_103261744","commands_not_successful":8,"consolidated_status":"passed","assigned_tunnel_id":"35055b2460004312968e16ba97f00652","error":null,"os":"Mac 10.10","breakpointed":null,"browser":"iphone"},{"browser_short_version":"8.0","video_url":"https://saucelabs.com/jobs/5809a98f3f154ad796244efd65e87ad2/video.flv","creation_time":1453175044,"custom-data":null,"browser_version":"8.0.","owner":"fcore","id":"5809a98f3f154ad796244efd65e87ad2","record_screenshots":true,"record_video":true,"build":"01-history-api_103261744","passed":true,"public":"public","end_time":1453175125,"status":"complete","log_url":"https://saucelabs.com/jobs/5809a98f3f154ad796244efd65e87ad2/selenium-server.log","start_time":1453175045,"proxied":true,"modification_time":1453175125,"tags":["103261744","1a3b410f3a27688727d8465d12cb3bdfc95dde98","fluxex"],"name":"FluxEx browser test for example: 01-history-api_103261744","commands_not_successful":8,"consolidated_status":"passed","assigned_tunnel_id":"35055b2460004312968e16ba97f00652","error":null,"os":"Mac 10.10","breakpointed":null,"browser":"ipad"},{"browser_short_version":"4.1","video_url":"https://saucelabs.com/jobs/3f2aacf06d6c4a2b8e2fa873f1945b4f/video.flv","creation_time":1453175044,"custom-data":null,"browser_version":"4.1.","owner":"fcore","id":"3f2aacf06d6c4a2b8e2fa873f1945b4f","record_screenshots":true,"record_video":true,"build":"01-history-api_103261744","passed":true,"public":"public","end_time":1453175095,"status":"complete","log_url":"https://saucelabs.com/jobs/3f2aacf06d6c4a2b8e2fa873f1945b4f/selenium-server.log","start_time":1453175044,"proxied":true,"modification_time":1453175096,"tags":["103261744","1a3b410f3a27688727d8465d12cb3bdfc95dde98","fluxex"],"name":"FluxEx browser test for example: 01-history-api_103261744","commands_not_successful":8,"consolidated_status":"passed","assigned_tunnel_id":"35055b2460004312968e16ba97f00652","error":null,"os":"Linux","breakpointed":null,"browser":"android"},{"browser_short_version":"47","video_url":"https://saucelabs.com/jobs/38271768fa764721b9f256a593bb7642/video.flv","creation_time":1453175044,"custom-data":null,"browser_version":"47.0.2526.73","owner":"fcore","id":"38271768fa764721b9f256a593bb7642","record_screenshots":true,"record_video":true,"build":"01-history-api_103261744","passed":false,"public":"public","end_time":1453175052,"status":"complete","log_url":"https://saucelabs.com/jobs/38271768fa764721b9f256a593bb7642/selenium-server.log","start_time":1453175044,"proxied":true,"modification_time":1453175052,"tags":["103261744","1a3b410f3a27688727d8465d12cb3bdfc95dde98","fluxex"],"name":"FluxEx browser test for example: 01-history-api_103261744","commands_not_successful":1,"consolidated_status":"failed","assigned_tunnel_id":"35055b2460004312968e16ba97f00652","error":null,"os":"Linux","breakpointed":null,"browser":"googlechrome"},{"browser_short_version":"4.4","video_url":"https://saucelabs.com/jobs/268d7d5cc59944928dc5c86ae3af7b94/video.flv","creation_time":1453175044,"custom-data":null,"browser_version":"4.4.","owner":"fcore","id":"268d7d5cc59944928dc5c86ae3af7b94","record_screenshots":true,"record_video":true,"build":"01-history-api_103261744","passed":true,"public":"public","end_time":1453175110,"status":"complete","log_url":"https://saucelabs.com/jobs/268d7d5cc59944928dc5c86ae3af7b94/selenium-server.log","start_time":1453175045,"proxied":true,"modification_time":1453175111,"tags":["103261744","1a3b410f3a27688727d8465d12cb3bdfc95dde98","fluxex"],"name":"FluxEx browser test for example: 01-history-api_103261744","commands_not_successful":8,"consolidated_status":"passed","assigned_tunnel_id":"35055b2460004312968e16ba97f00652","error":null,"os":"Linux","breakpointed":null,"browser":"android"},{"browser_short_version":"11","video_url":"https://saucelabs.com/jobs/01ac53d90fc94abd95b2781d8ea61c3a/video.flv","creation_time":1453175044,"custom-data":null,"browser_version":"11.0.9600.17801.","owner":"fcore","id":"01ac53d90fc94abd95b2781d8ea61c3a","record_screenshots":true,"record_video":true,"build":"01-history-api_103261744","passed":false,"public":"public","end_time":1453175056,"status":"complete","log_url":"https://saucelabs.com/jobs/01ac53d90fc94abd95b2781d8ea61c3a/selenium-server.log","start_time":1453175044,"proxied":true,"modification_time":1453175056,"tags":["103261744","1a3b410f3a27688727d8465d12cb3bdfc95dde98","fluxex"],"name":"FluxEx browser test for example: 01-history-api_103261744","commands_not_successful":1,"consolidated_status":"failed","assigned_tunnel_id":"35055b2460004312968e16ba97f00652","error":null,"os":"Windows 2012 R2","breakpointed":null,"browser":"iexplore"},{"browser_short_version":"6.1","video_url":"https://saucelabs.com/jobs/44790abdb7d44fdc8e21b1dce9c75fcc/video.flv","creation_time":1453175043,"custom-data":null,"browser_version":"6.1.","owner":"fcore","id":"44790abdb7d44fdc8e21b1dce9c75fcc","record_screenshots":true,"record_video":true,"build":"01-history-api_103261744","passed":true,"public":"public","end_time":1453175084,"status":"complete","log_url":"https://saucelabs.com/jobs/44790abdb7d44fdc8e21b1dce9c75fcc/selenium-server.log","start_time":1453175043,"proxied":true,"modification_time":1453175084,"tags":["103261744","1a3b410f3a27688727d8465d12cb3bdfc95dde98","fluxex"],"name":"FluxEx browser test for example: 01-history-api_103261744","commands_not_successful":10,"consolidated_status":"passed","assigned_tunnel_id":"35055b2460004312968e16ba97f00652","error":null,"os":"Mac 10.8","breakpointed":null,"browser":"ipad"},{"browser_short_version":"8.1","video_url":"https://saucelabs.com/jobs/3203855d36e24af2939e1dd7ec4a5c5a/video.flv","creation_time":1453175041,"custom-data":null,"browser_version":"8.1.","owner":"fcore","id":"3203855d36e24af2939e1dd7ec4a5c5a","record_screenshots":true,"record_video":true,"build":"01-history-api_103261744","passed":true,"public":"public","end_time":1453175130,"status":"complete","log_url":"https://saucelabs.com/jobs/3203855d36e24af2939e1dd7ec4a5c5a/selenium-server.log","start_time":1453175042,"proxied":true,"modification_time":1453175131,"tags":["103261744","1a3b410f3a27688727d8465d12cb3bdfc95dde98","fluxex"],"name":"FluxEx browser test for example: 01-history-api_103261744","commands_not_successful":8,"consolidated_status":"passed","assigned_tunnel_id":"35055b2460004312968e16ba97f00652","error":null,"os":"Mac 10.10","breakpointed":null,"browser":"ipad"},{"browser_short_version":"6.1","video_url":"https://saucelabs.com/jobs/529d9daf142f4c0f9da585fba41d6eb3/video.flv","creation_time":1453174801,"custom-data":null,"browser_version":"6.1.","owner":"fcore","id":"529d9daf142f4c0f9da585fba41d6eb3","record_screenshots":true,"record_video":true,"build":"00-simple-single-page_103261744","passed":true,"public":"public","end_time":1453174843,"status":"complete","log_url":"https://saucelabs.com/jobs/529d9daf142f4c0f9da585fba41d6eb3/selenium-server.log","start_time":1453174801,"proxied":true,"modification_time":1453174844,"tags":["103261744","1a3b410f3a27688727d8465d12cb3bdfc95dde98","fluxex"],"name":"FluxEx browser test for example: 00-simple-single-page_103261744","commands_not_successful":9,"consolidated_status":"passed","assigned_tunnel_id":"35055b2460004312968e16ba97f00652","error":null,"os":"Mac 10.8","breakpointed":null,"browser":"ipad"},{"browser_short_version":"7.1","video_url":"https://saucelabs.com/jobs/ffa07489302549a8995aab13c7b5f5d2/video.flv","creation_time":1453174800,"custom-data":null,"browser_version":"7.1.","owner":"fcore","id":"ffa07489302549a8995aab13c7b5f5d2","record_screenshots":true,"record_video":true,"build":"00-simple-single-page_103261744","passed":true,"public":"public","end_time":1453174863,"status":"complete","log_url":"https://saucelabs.com/jobs/ffa07489302549a8995aab13c7b5f5d2/selenium-server.log","start_time":1453174800,"proxied":true,"modification_time":1453174863,"tags":["103261744","1a3b410f3a27688727d8465d12cb3bdfc95dde98","fluxex"],"name":"FluxEx browser test for example: 00-simple-single-page_103261744","commands_not_successful":7,"consolidated_status":"passed","assigned_tunnel_id":"35055b2460004312968e16ba97f00652","error":null,"os":"Mac 10.9","breakpointed":null,"browser":"iphone"},{"browser_short_version":"10","video_url":"https://saucelabs.com/jobs/d133a63e31074c8782a7bc6d1b1c2566/video.flv","creation_time":1453174800,"custom-data":null,"browser_version":"10.0.9200.16580.","owner":"fcore","id":"d133a63e31074c8782a7bc6d1b1c2566","record_screenshots":true,"record_video":true,"build":"00-simple-single-page_103261744","passed":false,"public":"public","end_time":1453174812,"status":"complete","log_url":"https://saucelabs.com/jobs/d133a63e31074c8782a7bc6d1b1c2566/selenium-server.log","start_time":1453174801,"proxied":true,"modification_time":1453174813,"tags":["103261744","1a3b410f3a27688727d8465d12cb3bdfc95dde98","fluxex"],"name":"FluxEx browser test for example: 00-simple-single-page_103261744","commands_not_successful":1,"consolidated_status":"failed","assigned_tunnel_id":"35055b2460004312968e16ba97f00652","error":null,"os":"Windows 2012","breakpointed":null,"browser":"iexplore"},{"browser_short_version":"4.1","video_url":"https://saucelabs.com/jobs/cbea9b8bdf334ea28def20348281a70b/video.flv","creation_time":1453174800,"custom-data":null,"browser_version":"4.1.","owner":"fcore","id":"cbea9b8bdf334ea28def20348281a70b","record_screenshots":true,"record_video":true,"build":"00-simple-single-page_103261744","passed":true,"public":"public","end_time":1453174849,"status":"complete","log_url":"https://saucelabs.com/jobs/cbea9b8bdf334ea28def20348281a70b/selenium-server.log","start_time":1453174801,"proxied":true,"modification_time":1453174850,"tags":["103261744","1a3b410f3a27688727d8465d12cb3bdfc95dde98","fluxex"],"name":"FluxEx browser test for example: 00-simple-single-page_103261744","commands_not_successful":7,"consolidated_status":"passed","assigned_tunnel_id":"35055b2460004312968e16ba97f00652","error":null,"os":"Linux","breakpointed":null,"browser":"android"},{"browser_short_version":"6.1","video_url":"https://saucelabs.com/jobs/b1c675fe77294b4883d0d8797035824f/video.flv","creation_time":1453174800,"custom-data":null,"browser_version":"6.1.","owner":"fcore","id":"b1c675fe77294b4883d0d8797035824f","record_screenshots":true,"record_video":true,"build":"00-simple-single-page_103261744","passed":true,"public":"public","end_time":1453174843,"status":"complete","log_url":"https://saucelabs.com/jobs/b1c675fe77294b4883d0d8797035824f/selenium-server.log","start_time":1453174801,"proxied":true,"modification_time":1453174844,"tags":["103261744","1a3b410f3a27688727d8465d12cb3bdfc95dde98","fluxex"],"name":"FluxEx browser test for example: 00-simple-single-page_103261744","commands_not_successful":9,"consolidated_status":"passed","assigned_tunnel_id":"35055b2460004312968e16ba97f00652","error":null,"os":"Mac 10.8","breakpointed":null,"browser":"iphone"},{"browser_short_version":"8.0","video_url":"https://saucelabs.com/jobs/a749554a48b94ac286c9116baa35d2e3/video.flv","creation_time":1453174800,"custom-data":null,"browser_version":"8.0.","owner":"fcore","id":"a749554a48b94ac286c9116baa35d2e3","record_screenshots":true,"record_video":true,"build":"00-simple-single-page_103261744","passed":true,"public":"public","end_time":1453174882,"status":"complete","log_url":"https://saucelabs.com/jobs/a749554a48b94ac286c9116baa35d2e3/selenium-server.log","start_time":1453174800,"proxied":true,"modification_time":1453174883,"tags":["103261744","1a3b410f3a27688727d8465d12cb3bdfc95dde98","fluxex"],"name":"FluxEx browser test for example: 00-simple-single-page_103261744","commands_not_successful":7,"consolidated_status":"passed","assigned_tunnel_id":"35055b2460004312968e16ba97f00652","error":null,"os":"Mac 10.10","breakpointed":null,"browser":"ipad"},{"browser_short_version":"8.1","video_url":"https://saucelabs.com/jobs/7471443089864fe2b2faa2f0b0433c74/video.flv","creation_time":1453174800,"custom-data":null,"browser_version":"8.1.","owner":"fcore","id":"7471443089864fe2b2faa2f0b0433c74","record_screenshots":true,"record_video":true,"build":"00-simple-single-page_103261744","passed":true,"public":"public","end_time":1453174890,"status":"complete","log_url":"https://saucelabs.com/jobs/7471443089864fe2b2faa2f0b0433c74/selenium-server.log","start_time":1453174801,"proxied":true,"modification_time":1453174890,"tags":["103261744","1a3b410f3a27688727d8465d12cb3bdfc95dde98","fluxex"],"name":"FluxEx browser test for example: 00-simple-single-page_103261744","commands_not_successful":7,"consolidated_status":"passed","assigned_tunnel_id":"35055b2460004312968e16ba97f00652","error":null,"os":"Mac 10.10","breakpointed":null,"browser":"ipad"},{"browser_short_version":"8.0","video_url":"https://saucelabs.com/jobs/71e45822428f48658166695513ed92ae/video.flv","creation_time":1453174800,"custom-data":null,"browser_version":"8.0.","owner":"fcore","id":"71e45822428f48658166695513ed92ae","record_screenshots":true,"record_video":true,"build":"00-simple-single-page_103261744","passed":true,"public":"public","end_time":1453174891,"status":"complete","log_url":"https://saucelabs.com/jobs/71e45822428f48658166695513ed92ae/selenium-server.log","start_time":1453174801,"proxied":true,"modification_time":1453174891,"tags":["103261744","1a3b410f3a27688727d8465d12cb3bdfc95dde98","fluxex"],"name":"FluxEx browser test for example: 00-simple-single-page_103261744","commands_not_successful":7,"consolidated_status":"passed","assigned_tunnel_id":"35055b2460004312968e16ba97f00652","error":null,"os":"Mac 10.10","breakpointed":null,"browser":"iphone"},{"browser_short_version":"4.4","video_url":"https://saucelabs.com/jobs/63ecc1ae6f5a418694cc98873f3190ce/video.flv","creation_time":1453174800,"custom-data":null,"browser_version":"4.4.","owner":"fcore","id":"63ecc1ae6f5a418694cc98873f3190ce","record_screenshots":true,"record_video":true,"build":"00-simple-single-page_103261744","passed":true,"public":"public","end_time":1453174865,"status":"complete","log_url":"https://saucelabs.com/jobs/63ecc1ae6f5a418694cc98873f3190ce/selenium-server.log","start_time":1453174800,"proxied":true,"modification_time":1453174865,"tags":["103261744","1a3b410f3a27688727d8465d12cb3bdfc95dde98","fluxex"],"name":"FluxEx browser test for example: 00-simple-single-page_103261744","commands_not_successful":7,"consolidated_status":"passed","assigned_tunnel_id":"35055b2460004312968e16ba97f00652","error":null,"os":"Linux","breakpointed":null,"browser":"android"},{"browser_short_version":"7","video_url":"https://saucelabs.com/jobs/5822a95cf7f749c0ae7dcb94107896c5/video.flv","creation_time":1453174800,"custom-data":null,"browser_version":"7.0.","owner":"fcore","id":"5822a95cf7f749c0ae7dcb94107896c5","record_screenshots":true,"record_video":true,"build":"00-simple-single-page_103261744","passed":true,"public":"public","end_time":1453174828,"status":"complete","log_url":"https://saucelabs.com/jobs/5822a95cf7f749c0ae7dcb94107896c5/selenium-server.log","start_time":1453174800,"proxied":true,"modification_time":1453174828,"tags":["103261744","1a3b410f3a27688727d8465d12cb3bdfc95dde98","fluxex"],"name":"FluxEx browser test for example: 00-simple-single-page_103261744","commands_not_successful":3,"consolidated_status":"passed","assigned_tunnel_id":"35055b2460004312968e16ba97f00652","error":null,"os":"Mac 10.9","breakpointed":null,"browser":"safari"},{"browser_short_version":"4.0","video_url":"https://saucelabs.com/jobs/57a7bf3fbaf44b3f8ccd39b36337fd85/video.flv","creation_time":1453174800,"custom-data":null,"browser_version":"4.0.4.","owner":"fcore","id":"57a7bf3fbaf44b3f8ccd39b36337fd85","record_screenshots":true,"record_video":true,"build":"00-simple-single-page_103261744","passed":true,"public":"public","end_time":1453174851,"status":"complete","log_url":"https://saucelabs.com/jobs/57a7bf3fbaf44b3f8ccd39b36337fd85/selenium-server.log","start_time":1453174801,"proxied":true,"modification_time":1453174851,"tags":["103261744","1a3b410f3a27688727d8465d12cb3bdfc95dde98","fluxex"],"name":"FluxEx browser test for example: 00-simple-single-page_103261744","commands_not_successful":7,"consolidated_status":"passed","assigned_tunnel_id":"35055b2460004312968e16ba97f00652","error":null,"os":"Linux","breakpointed":null,"browser":"android"},{"browser_short_version":"8.1","video_url":"https://saucelabs.com/jobs/53d031767e2749858312a84c67de4fb7/video.flv","creation_time":1453174800,"custom-data":null,"browser_version":"8.1.","owner":"fcore","id":"53d031767e2749858312a84c67de4fb7","record_screenshots":true,"record_video":true,"build":"00-simple-single-page_103261744","passed":true,"public":"public","end_time":1453174885,"status":"complete","log_url":"https://saucelabs.com/jobs/53d031767e2749858312a84c67de4fb7/selenium-server.log","start_time":1453174801,"proxied":true,"modification_time":1453174886,"tags":["103261744","1a3b410f3a27688727d8465d12cb3bdfc95dde98","fluxex"],"name":"FluxEx browser test for example: 00-simple-single-page_103261744","commands_not_successful":7,"consolidated_status":"passed","assigned_tunnel_id":"35055b2460004312968e16ba97f00652","error":null,"os":"Mac 10.10","breakpointed":null,"browser":"iphone"},{"browser_short_version":"7.1","video_url":"https://saucelabs.com/jobs/3528a370a2b94cf2984d880a410b5607/video.flv","creation_time":1453174800,"custom-data":null,"browser_version":"7.1.","owner":"fcore","id":"3528a370a2b94cf2984d880a410b5607","record_screenshots":true,"record_video":true,"build":"00-simple-single-page_103261744","passed":true,"public":"public","end_time":1453174977,"status":"complete","log_url":"https://saucelabs.com/jobs/3528a370a2b94cf2984d880a410b5607/selenium-server.log","start_time":1453174801,"proxied":true,"modification_time":1453174977,"tags":["103261744","1a3b410f3a27688727d8465d12cb3bdfc95dde98","fluxex"],"name":"FluxEx browser test for example: 00-simple-single-page_103261744","commands_not_successful":7,"consolidated_status":"passed","assigned_tunnel_id":"35055b2460004312968e16ba97f00652","error":null,"os":"Mac 10.9","breakpointed":null,"browser":"ipad"},{"browser_short_version":"6","video_url":"https://saucelabs.com/jobs/0e81922d5b7e4d2fa27f4277bdad230a/video.flv","creation_time":1453174800,"custom-data":null,"browser_version":"6.0.4.","owner":"fcore","id":"0e81922d5b7e4d2fa27f4277bdad230a","record_screenshots":true,"record_video":true,"build":"00-simple-single-page_103261744","passed":true,"public":"public","end_time":1453174820,"status":"complete","log_url":"https://saucelabs.com/jobs/0e81922d5b7e4d2fa27f4277bdad230a/selenium-server.log","start_time":1453174800,"proxied":true,"modification_time":1453174820,"tags":["103261744","1a3b410f3a27688727d8465d12cb3bdfc95dde98","fluxex"],"name":"FluxEx browser test for example: 00-simple-single-page_103261744","commands_not_successful":3,"consolidated_status":"passed","assigned_tunnel_id":"35055b2460004312968e16ba97f00652","error":null,"os":"Mac 10.8","breakpointed":null,"browser":"safari"},{"browser_short_version":"8","video_url":"https://saucelabs.com/jobs/f4a729831eb24ccebcf6cdba5fbba3c7/video.flv","creation_time":1453174799,"custom-data":null,"browser_version":"8.0.7601.17514.","owner":"fcore","id":"f4a729831eb24ccebcf6cdba5fbba3c7","record_screenshots":true,"record_video":true,"build":"00-simple-single-page_103261744","passed":false,"public":"public","end_time":1453174811,"status":"complete","log_url":"https://saucelabs.com/jobs/f4a729831eb24ccebcf6cdba5fbba3c7/selenium-server.log","start_time":1453174799,"proxied":true,"modification_time":1453174811,"tags":["103261744","1a3b410f3a27688727d8465d12cb3bdfc95dde98","fluxex"],"name":"FluxEx browser test for example: 00-simple-single-page_103261744","commands_not_successful":1,"consolidated_status":"failed","assigned_tunnel_id":"35055b2460004312968e16ba97f00652","error":null,"os":"Windows 2008","breakpointed":null,"browser":"iexplore"},{"browser_short_version":"47","video_url":"https://saucelabs.com/jobs/dab4936fb6914d5eaf721eb3b30153aa/video.flv","creation_time":1453174799,"custom-data":null,"browser_version":"47.0.2526.73","owner":"fcore","id":"dab4936fb6914d5eaf721eb3b30153aa","record_screenshots":true,"record_video":true,"build":"00-simple-single-page_103261744","passed":false,"public":"public","end_time":1453174807,"status":"complete","log_url":"https://saucelabs.com/jobs/dab4936fb6914d5eaf721eb3b30153aa/selenium-server.log","start_time":1453174800,"proxied":true,"modification_time":1453174808,"tags":["103261744","1a3b410f3a27688727d8465d12cb3bdfc95dde98","fluxex"],"name":"FluxEx browser test for example: 00-simple-single-page_103261744","commands_not_successful":1,"consolidated_status":"failed","assigned_tunnel_id":"35055b2460004312968e16ba97f00652","error":null,"os":"Linux","breakpointed":null,"browser":"googlechrome"},{"browser_short_version":"34","video_url":"https://saucelabs.com/jobs/99e0ca060141424f94097e19f1ee3f77/video.flv","creation_time":1453174799,"custom-data":null,"browser_version":"34.0.","owner":"fcore","id":"99e0ca060141424f94097e19f1ee3f77","record_screenshots":true,"record_video":true,"build":"00-simple-single-page_103261744","passed":false,"public":"public","end_time":1453174810,"status":"complete","log_url":"https://saucelabs.com/jobs/99e0ca060141424f94097e19f1ee3f77/selenium-server.log","start_time":1453174799,"proxied":true,"modification_time":1453174811,"tags":["103261744","1a3b410f3a27688727d8465d12cb3bdfc95dde98","fluxex"],"name":"FluxEx browser test for example: 00-simple-single-page_103261744","commands_not_successful":1,"consolidated_status":"failed","assigned_tunnel_id":"35055b2460004312968e16ba97f00652","error":null,"os":"Linux","breakpointed":null,"browser":"firefox"},{"browser_short_version":"9","video_url":"https://saucelabs.com/jobs/919bb8c83ea542f3844b0d753f66cc70/video.flv","creation_time":1453174798,"custom-data":null,"browser_version":"9.0.8112.16421.","owner":"fcore","id":"919bb8c83ea542f3844b0d753f66cc70","record_screenshots":true,"record_video":true,"build":"00-simple-single-page_103261744","passed":false,"public":"public","end_time":1453174813,"status":"complete","log_url":"https://saucelabs.com/jobs/919bb8c83ea542f3844b0d753f66cc70/selenium-server.log","start_time":1453174799,"proxied":true,"modification_time":1453174813,"tags":["103261744","1a3b410f3a27688727d8465d12cb3bdfc95dde98","fluxex"],"name":"FluxEx browser test for example: 00-simple-single-page_103261744","commands_not_successful":1,"consolidated_status":"failed","assigned_tunnel_id":"35055b2460004312968e16ba97f00652","error":null,"os":"Windows 2008","breakpointed":null,"browser":"iexplore"},{"browser_short_version":"11","video_url":"https://saucelabs.com/jobs/55080ae0c25044dc90d0427e452ea4ef/video.flv","creation_time":1453174798,"custom-data":null,"browser_version":"11.0.9600.17801.","owner":"fcore","id":"55080ae0c25044dc90d0427e452ea4ef","record_screenshots":true,"record_video":true,"build":"00-simple-single-page_103261744","passed":false,"public":"public","end_time":1453174810,"status":"complete","log_url":"https://saucelabs.com/jobs/55080ae0c25044dc90d0427e452ea4ef/selenium-server.log","start_time":1453174799,"proxied":true,"modification_time":1453174810,"tags":["103261744","1a3b410f3a27688727d8465d12cb3bdfc95dde98","fluxex"],"name":"FluxEx browser test for example: 00-simple-single-page_103261744","commands_not_successful":1,"consolidated_status":"failed","assigned_tunnel_id":"35055b2460004312968e16ba97f00652","error":null,"os":"Windows 2012 R2","breakpointed":null,"browser":"iexplore"},{"browser_short_version":"4.0","video_url":"https://saucelabs.com/jobs/f214bc6d6df24f4e94b6ca198abd7a1a/video.flv","creation_time":1453174507,"custom-data":null,"browser_version":"4.0.4.","owner":"fcore","id":"f214bc6d6df24f4e94b6ca198abd7a1a","record_screenshots":true,"record_video":true,"build":"00hello_103261341","passed":true,"public":"public","end_time":1453174556,"status":"complete","log_url":"https://saucelabs.com/jobs/f214bc6d6df24f4e94b6ca198abd7a1a/selenium-server.log","start_time":1453174507,"proxied":true,"modification_time":1453174556,"tags":["103261341","45c8094b21f948cc527c75d2e816a8da3d3d6954","fluxex"],"name":"FluxEx browser test for example: 00hello_103261341","commands_not_successful":7,"consolidated_status":"passed","assigned_tunnel_id":"f4ee57717e5e40ce92492ec21a973f9f","error":null,"os":"Linux","breakpointed":null,"browser":"android"},{"browser_short_version":"8.1","video_url":"https://saucelabs.com/jobs/ef460f4c959f4f52a8e8a4f45de7a282/video.flv","creation_time":1453174507,"custom-data":null,"browser_version":"8.1.","owner":"fcore","id":"ef460f4c959f4f52a8e8a4f45de7a282","record_screenshots":true,"record_video":true,"build":"00hello_103261341","passed":true,"public":"public","end_time":1453174592,"status":"complete","log_url":"https://saucelabs.com/jobs/ef460f4c959f4f52a8e8a4f45de7a282/selenium-server.log","start_time":1453174507,"proxied":true,"modification_time":1453174592,"tags":["103261341","45c8094b21f948cc527c75d2e816a8da3d3d6954","fluxex"],"name":"FluxEx browser test for example: 00hello_103261341","commands_not_successful":7,"consolidated_status":"passed","assigned_tunnel_id":"f4ee57717e5e40ce92492ec21a973f9f","error":null,"os":"Mac 10.10","breakpointed":null,"browser":"iphone"},{"browser_short_version":"8","video_url":"https://saucelabs.com/jobs/e7b408413ec8475c87e97687fd4734b2/video.flv","creation_time":1453174507,"custom-data":null,"browser_version":"8.0.7601.17514.","owner":"fcore","id":"e7b408413ec8475c87e97687fd4734b2","record_screenshots":true,"record_video":true,"build":"00hello_103261341","passed":false,"public":"public","end_time":1453174519,"status":"complete","log_url":"https://saucelabs.com/jobs/e7b408413ec8475c87e97687fd4734b2/selenium-server.log","start_time":1453174507,"proxied":true,"modification_time":1453174519,"tags":["103261341","45c8094b21f948cc527c75d2e816a8da3d3d6954","fluxex"],"name":"FluxEx browser test for example: 00hello_103261341","commands_not_successful":3,"consolidated_status":"failed","assigned_tunnel_id":"f4ee57717e5e40ce92492ec21a973f9f","error":null,"os":"Windows 2008","breakpointed":null,"browser":"iexplore"},{"browser_short_version":"8.0","video_url":"https://saucelabs.com/jobs/dddbca1917cd4f51bbe6628a8b5f62c4/video.flv","creation_time":1453174507,"custom-data":null,"browser_version":"8.0.","owner":"fcore","id":"dddbca1917cd4f51bbe6628a8b5f62c4","record_screenshots":true,"record_video":true,"build":"00hello_103261341","passed":true,"public":"public","end_time":1453174601,"status":"complete","log_url":"https://saucelabs.com/jobs/dddbca1917cd4f51bbe6628a8b5f62c4/selenium-server.log","start_time":1453174507,"proxied":true,"modification_time":1453174601,"tags":["103261341","45c8094b21f948cc527c75d2e816a8da3d3d6954","fluxex"],"name":"FluxEx browser test for example: 00hello_103261341","commands_not_successful":7,"consolidated_status":"passed","assigned_tunnel_id":"f4ee57717e5e40ce92492ec21a973f9f","error":null,"os":"Mac 10.10","breakpointed":null,"browser":"iphone"},{"browser_short_version":"7.1","video_url":"https://saucelabs.com/jobs/b708a786fbfe4a4a9fc532c2e70c9ecb/video.flv","creation_time":1453174507,"custom-data":null,"browser_version":"7.1.","owner":"fcore","id":"b708a786fbfe4a4a9fc532c2e70c9ecb","record_screenshots":true,"record_video":true,"build":"00hello_103261341","passed":true,"public":"public","end_time":1453174618,"status":"complete","log_url":"https://saucelabs.com/jobs/b708a786fbfe4a4a9fc532c2e70c9ecb/selenium-server.log","start_time":1453174507,"proxied":true,"modification_time":1453174618,"tags":["103261341","45c8094b21f948cc527c75d2e816a8da3d3d6954","fluxex"],"name":"FluxEx browser test for example: 00hello_103261341","commands_not_successful":7,"consolidated_status":"passed","assigned_tunnel_id":"f4ee57717e5e40ce92492ec21a973f9f","error":null,"os":"Mac 10.9","breakpointed":null,"browser":"ipad"},{"browser_short_version":"8.0","video_url":"https://saucelabs.com/jobs/8016ecafbeb24464bec35a3f2fd1ef9d/video.flv","creation_time":1453174507,"custom-data":null,"browser_version":"8.0.","owner":"fcore","id":"8016ecafbeb24464bec35a3f2fd1ef9d","record_screenshots":true,"record_video":true,"build":"00hello_103261341","passed":true,"public":"public","end_time":1453174582,"status":"complete","log_url":"https://saucelabs.com/jobs/8016ecafbeb24464bec35a3f2fd1ef9d/selenium-server.log","start_time":1453174507,"proxied":true,"modification_time":1453174582,"tags":["103261341","45c8094b21f948cc527c75d2e816a8da3d3d6954","fluxex"],"name":"FluxEx browser test for example: 00hello_103261341","commands_not_successful":7,"consolidated_status":"passed","assigned_tunnel_id":"f4ee57717e5e40ce92492ec21a973f9f","error":null,"os":"Mac 10.10","breakpointed":null,"browser":"ipad"},{"browser_short_version":"4.4","video_url":"https://saucelabs.com/jobs/6305b7d24f6e4885b5eedb196d333597/video.flv","creation_time":1453174507,"custom-data":null,"browser_version":"4.4.","owner":"fcore","id":"6305b7d24f6e4885b5eedb196d333597","record_screenshots":true,"record_video":true,"build":"00hello_103261341","passed":true,"public":"public","end_time":1453174580,"status":"complete","log_url":"https://saucelabs.com/jobs/6305b7d24f6e4885b5eedb196d333597/selenium-server.log","start_time":1453174507,"proxied":true,"modification_time":1453174581,"tags":["103261341","45c8094b21f948cc527c75d2e816a8da3d3d6954","fluxex"],"name":"FluxEx browser test for example: 00hello_103261341","commands_not_successful":7,"consolidated_status":"passed","assigned_tunnel_id":"f4ee57717e5e40ce92492ec21a973f9f","error":null,"os":"Linux","breakpointed":null,"browser":"android"},{"browser_short_version":"7.1","video_url":"https://saucelabs.com/jobs/34bfec20d51740a8a8b5dcc86651cf83/video.flv","creation_time":1453174507,"custom-data":null,"browser_version":"7.1.","owner":"fcore","id":"34bfec20d51740a8a8b5dcc86651cf83","record_screenshots":true,"record_video":true,"build":"00hello_103261341","passed":true,"public":"public","end_time":1453174636,"status":"complete","log_url":"https://saucelabs.com/jobs/34bfec20d51740a8a8b5dcc86651cf83/selenium-server.log","start_time":1453174507,"proxied":true,"modification_time":1453174636,"tags":["103261341","45c8094b21f948cc527c75d2e816a8da3d3d6954","fluxex"],"name":"FluxEx browser test for example: 00hello_103261341","commands_not_successful":7,"consolidated_status":"passed","assigned_tunnel_id":"f4ee57717e5e40ce92492ec21a973f9f","error":null,"os":"Mac 10.9","breakpointed":null,"browser":"iphone"},{"browser_short_version":"6.1","video_url":"https://saucelabs.com/jobs/02a0e534ece549daae2a840fc7494e74/video.flv","creation_time":1453174507,"custom-data":null,"browser_version":"6.1.","owner":"fcore","id":"02a0e534ece549daae2a840fc7494e74","record_screenshots":true,"record_video":true,"build":"00hello_103261341","passed":true,"public":"public","end_time":1453174549,"status":"complete","log_url":"https://saucelabs.com/jobs/02a0e534ece549daae2a840fc7494e74/selenium-server.log","start_time":1453174507,"proxied":true,"modification_time":1453174549,"tags":["103261341","45c8094b21f948cc527c75d2e816a8da3d3d6954","fluxex"],"name":"FluxEx browser test for example: 00hello_103261341","commands_not_successful":9,"consolidated_status":"passed","assigned_tunnel_id":"f4ee57717e5e40ce92492ec21a973f9f","error":null,"os":"Mac 10.8","breakpointed":null,"browser":"ipad"},{"browser_short_version":"34","video_url":"https://saucelabs.com/jobs/f577d17b662a45d88a001946c469b37b/video.flv","creation_time":1453174506,"custom-data":null,"browser_version":"34.0.","owner":"fcore","id":"f577d17b662a45d88a001946c469b37b","record_screenshots":true,"record_video":true,"build":"00hello_103261341","passed":false,"public":"public","end_time":1453174519,"status":"complete","log_url":"https://saucelabs.com/jobs/f577d17b662a45d88a001946c469b37b/selenium-server.log","start_time":1453174506,"proxied":true,"modification_time":1453174519,"tags":["103261341","45c8094b21f948cc527c75d2e816a8da3d3d6954","fluxex"],"name":"FluxEx browser test for example: 00hello_103261341","commands_not_successful":3,"consolidated_status":"failed","assigned_tunnel_id":"f4ee57717e5e40ce92492ec21a973f9f","error":null,"os":"Linux","breakpointed":null,"browser":"firefox"},{"browser_short_version":"10","video_url":"https://saucelabs.com/jobs/b18242dbe74343b3bc448b8a433dbc46/video.flv","creation_time":1453174506,"custom-data":null,"browser_version":"10.0.9200.16580.","owner":"fcore","id":"b18242dbe74343b3bc448b8a433dbc46","record_screenshots":true,"record_video":true,"build":"00hello_103261341","passed":true,"public":"public","end_time":1453174523,"status":"complete","log_url":"https://saucelabs.com/jobs/b18242dbe74343b3bc448b8a433dbc46/selenium-server.log","start_time":1453174507,"proxied":true,"modification_time":1453174523,"tags":["103261341","45c8094b21f948cc527c75d2e816a8da3d3d6954","fluxex"],"name":"FluxEx browser test for example: 00hello_103261341","commands_not_successful":3,"consolidated_status":"passed","assigned_tunnel_id":"f4ee57717e5e40ce92492ec21a973f9f","error":null,"os":"Windows 2012","breakpointed":null,"browser":"iexplore"},{"browser_short_version":"4.1","video_url":"https://saucelabs.com/jobs/b163a904d4df4600bffe0014a8a594cb/video.flv","creation_time":1453174506,"custom-data":null,"browser_version":"4.1.","owner":"fcore","id":"b163a904d4df4600bffe0014a8a594cb","record_screenshots":true,"record_video":true,"build":"00hello_103261341","passed":true,"public":"public","end_time":1453174556,"status":"complete","log_url":"https://saucelabs.com/jobs/b163a904d4df4600bffe0014a8a594cb/selenium-server.log","start_time":1453174507,"proxied":true,"modification_time":1453174556,"tags":["103261341","45c8094b21f948cc527c75d2e816a8da3d3d6954","fluxex"],"name":"FluxEx browser test for example: 00hello_103261341","commands_not_successful":7,"consolidated_status":"passed","assigned_tunnel_id":"f4ee57717e5e40ce92492ec21a973f9f","error":null,"os":"Linux","breakpointed":null,"browser":"android"},{"browser_short_version":"8.1","video_url":"https://saucelabs.com/jobs/8d5ed238c3bf469a86d8d4543c00184a/video.flv","creation_time":1453174506,"custom-data":null,"browser_version":"8.1.","owner":"fcore","id":"8d5ed238c3bf469a86d8d4543c00184a","record_screenshots":true,"record_video":true,"build":"00hello_103261341","passed":true,"public":"public","end_time":1453174612,"status":"complete","log_url":"https://saucelabs.com/jobs/8d5ed238c3bf469a86d8d4543c00184a/selenium-server.log","start_time":1453174507,"proxied":true,"modification_time":1453174612,"tags":["103261341","45c8094b21f948cc527c75d2e816a8da3d3d6954","fluxex"],"name":"FluxEx browser test for example: 00hello_103261341","commands_not_successful":7,"consolidated_status":"passed","assigned_tunnel_id":"f4ee57717e5e40ce92492ec21a973f9f","error":null,"os":"Mac 10.10","breakpointed":null,"browser":"ipad"},{"browser_short_version":"47","video_url":"https://saucelabs.com/jobs/7002eb7066ca45e289d453ae42672b65/video.flv","creation_time":1453174506,"custom-data":null,"browser_version":"47.0.2526.73","owner":"fcore","id":"7002eb7066ca45e289d453ae42672b65","record_screenshots":true,"record_video":true,"build":"00hello_103261341","passed":false,"public":"public","end_time":1453174512,"status":"complete","log_url":"https://saucelabs.com/jobs/7002eb7066ca45e289d453ae42672b65/selenium-server.log","start_time":1453174506,"proxied":true,"modification_time":1453174512,"tags":["103261341","45c8094b21f948cc527c75d2e816a8da3d3d6954","fluxex"],"name":"FluxEx browser test for example: 00hello_103261341","commands_not_successful":1,"consolidated_status":"failed","assigned_tunnel_id":"f4ee57717e5e40ce92492ec21a973f9f","error":null,"os":"Linux","breakpointed":null,"browser":"googlechrome"},{"browser_short_version":"7","video_url":"https://saucelabs.com/jobs/67974e33f78b4f2eb23ccbb258c6aea3/video.flv","creation_time":1453174506,"custom-data":null,"browser_version":"7.0.","owner":"fcore","id":"67974e33f78b4f2eb23ccbb258c6aea3","record_screenshots":true,"record_video":true,"build":"00hello_103261341","passed":true,"public":"public","end_time":1453174534,"status":"complete","log_url":"https://saucelabs.com/jobs/67974e33f78b4f2eb23ccbb258c6aea3/selenium-server.log","start_time":1453174507,"proxied":true,"modification_time":1453174535,"tags":["103261341","45c8094b21f948cc527c75d2e816a8da3d3d6954","fluxex"],"name":"FluxEx browser test for example: 00hello_103261341","commands_not_successful":3,"consolidated_status":"passed","assigned_tunnel_id":"f4ee57717e5e40ce92492ec21a973f9f","error":null,"os":"Mac 10.9","breakpointed":null,"browser":"safari"},{"browser_short_version":"6.1","video_url":"https://saucelabs.com/jobs/445f02320489405d97e3a065fe469472/video.flv","creation_time":1453174506,"custom-data":null,"browser_version":"6.1.","owner":"fcore","id":"445f02320489405d97e3a065fe469472","record_screenshots":true,"record_video":true,"build":"00hello_103261341","passed":true,"public":"public","end_time":1453174546,"status":"complete","log_url":"https://saucelabs.com/jobs/445f02320489405d97e3a065fe469472/selenium-server.log","start_time":1453174507,"proxied":true,"modification_time":1453174546,"tags":["103261341","45c8094b21f948cc527c75d2e816a8da3d3d6954","fluxex"],"name":"FluxEx browser test for example: 00hello_103261341","commands_not_successful":9,"consolidated_status":"passed","assigned_tunnel_id":"f4ee57717e5e40ce92492ec21a973f9f","error":null,"os":"Mac 10.8","breakpointed":null,"browser":"iphone"},{"browser_short_version":"11","video_url":"https://saucelabs.com/jobs/25255300746a40bfae7206ce2a1645a4/video.flv","creation_time":1453174506,"custom-data":null,"browser_version":"11.0.9600.17801.","owner":"fcore","id":"25255300746a40bfae7206ce2a1645a4","record_screenshots":true,"record_video":true,"build":"00hello_103261341","passed":true,"public":"public","end_time":1453174523,"status":"complete","log_url":"https://saucelabs.com/jobs/25255300746a40bfae7206ce2a1645a4/selenium-server.log","start_time":1453174507,"proxied":true,"modification_time":1453174523,"tags":["103261341","45c8094b21f948cc527c75d2e816a8da3d3d6954","fluxex"],"name":"FluxEx browser test for example: 00hello_103261341","commands_not_successful":3,"consolidated_status":"passed","assigned_tunnel_id":"f4ee57717e5e40ce92492ec21a973f9f","error":null,"os":"Windows 2012 R2","breakpointed":null,"browser":"iexplore"},{"browser_short_version":"6","video_url":"https://saucelabs.com/jobs/192ca442b5e249e59c888b8573be5d53/video.flv","creation_time":1453174506,"custom-data":null,"browser_version":"6.0.4.","owner":"fcore","id":"192ca442b5e249e59c888b8573be5d53","record_screenshots":true,"record_video":true,"build":"00hello_103261341","passed":true,"public":"public","end_time":1453174522,"status":"complete","log_url":"https://saucelabs.com/jobs/192ca442b5e249e59c888b8573be5d53/selenium-server.log","start_time":1453174507,"proxied":true,"modification_time":1453174522,"tags":["103261341","45c8094b21f948cc527c75d2e816a8da3d3d6954","fluxex"],"name":"FluxEx browser test for example: 00hello_103261341","commands_not_successful":3,"consolidated_status":"passed","assigned_tunnel_id":"f4ee57717e5e40ce92492ec21a973f9f","error":null,"os":"Mac 10.8","breakpointed":null,"browser":"safari"},{"browser_short_version":"9","video_url":"https://saucelabs.com/jobs/15f50e11312d44cbab64ba5ad6683562/video.flv","creation_time":1453174506,"custom-data":null,"browser_version":"9.0.8112.16421.","owner":"fcore","id":"15f50e11312d44cbab64ba5ad6683562","record_screenshots":true,"record_video":true,"build":"00hello_103261341","passed":true,"public":"public","end_time":1453174525,"status":"complete","log_url":"https://saucelabs.com/jobs/15f50e11312d44cbab64ba5ad6683562/selenium-server.log","start_time":1453174507,"proxied":true,"modification_time":1453174526,"tags":["103261341","45c8094b21f948cc527c75d2e816a8da3d3d6954","fluxex"],"name":"FluxEx browser test for example: 00hello_103261341","commands_not_successful":3,"consolidated_status":"passed","assigned_tunnel_id":"f4ee57717e5e40ce92492ec21a973f9f","error":null,"os":"Windows 2008","breakpointed":null,"browser":"iexplore"},{"browser_short_version":"8.1","video_url":"https://saucelabs.com/jobs/f41b000fbd084491b80fc688dfa669e2/video.flv","creation_time":1453169739,"custom-data":null,"browser_version":"8.1.","owner":"fcore","id":"f41b000fbd084491b80fc688dfa669e2","record_screenshots":true,"record_video":true,"build":"04-infinite-scroll_103250746","passed":false,"public":"public","end_time":1453169826,"status":"complete","log_url":"https://saucelabs.com/jobs/f41b000fbd084491b80fc688dfa669e2/selenium-server.log","start_time":1453169739,"proxied":true,"modification_time":1453169826,"tags":["103250746","f474ee7433ef972b13bfe27995acc773e8cdba91","fluxex"],"name":"FluxEx browser test for example: 04-infinite-scroll_103250746","commands_not_successful":4,"consolidated_status":"failed","assigned_tunnel_id":"333f633b417a42e48343b14d80caacc8","error":null,"os":"Mac 10.10","breakpointed":null,"browser":"ipad"},{"browser_short_version":"7.1","video_url":"https://saucelabs.com/jobs/f22e6f451e4040e0b8b65040ea0c3667/video.flv","creation_time":1453169739,"custom-data":null,"browser_version":"7.1.","owner":"fcore","id":"f22e6f451e4040e0b8b65040ea0c3667","record_screenshots":true,"record_video":true,"build":"04-infinite-scroll_103250746","passed":true,"public":"public","end_time":1453169855,"status":"complete","log_url":"https://saucelabs.com/jobs/f22e6f451e4040e0b8b65040ea0c3667/selenium-server.log","start_time":1453169739,"proxied":true,"modification_time":1453169856,"tags":["103250746","f474ee7433ef972b13bfe27995acc773e8cdba91","fluxex"],"name":"FluxEx browser test for example: 04-infinite-scroll_103250746","commands_not_successful":5,"consolidated_status":"passed","assigned_tunnel_id":"333f633b417a42e48343b14d80caacc8","error":null,"os":"Mac 10.9","breakpointed":null,"browser":"ipad"},{"browser_short_version":"6.1","video_url":"https://saucelabs.com/jobs/ae4bc115f2e44f379a8a76296b0cd866/video.flv","creation_time":1453169739,"custom-data":null,"browser_version":"6.1.","owner":"fcore","id":"ae4bc115f2e44f379a8a76296b0cd866","record_screenshots":true,"record_video":true,"build":"04-infinite-scroll_103250746","passed":true,"public":"public","end_time":1453169785,"status":"complete","log_url":"https://saucelabs.com/jobs/ae4bc115f2e44f379a8a76296b0cd866/selenium-server.log","start_time":1453169739,"proxied":true,"modification_time":1453169785,"tags":["103250746","f474ee7433ef972b13bfe27995acc773e8cdba91","fluxex"],"name":"FluxEx browser test for example: 04-infinite-scroll_103250746","commands_not_successful":6,"consolidated_status":"passed","assigned_tunnel_id":"333f633b417a42e48343b14d80caacc8","error":null,"os":"Mac 10.8","breakpointed":null,"browser":"ipad"},{"browser_short_version":"8.0","video_url":"https://saucelabs.com/jobs/1aa174630257487f937ba66daca1b4d2/video.flv","creation_time":1453169739,"custom-data":null,"browser_version":"8.0.","owner":"fcore","id":"1aa174630257487f937ba66daca1b4d2","record_screenshots":true,"record_video":true,"build":"04-infinite-scroll_103250746","passed":false,"public":"public","end_time":1453169810,"status":"complete","log_url":"https://saucelabs.com/jobs/1aa174630257487f937ba66daca1b4d2/selenium-server.log","start_time":1453169739,"proxied":true,"modification_time":1453169811,"tags":["103250746","f474ee7433ef972b13bfe27995acc773e8cdba91","fluxex"],"name":"FluxEx browser test for example: 04-infinite-scroll_103250746","commands_not_successful":4,"consolidated_status":"failed","assigned_tunnel_id":"333f633b417a42e48343b14d80caacc8","error":null,"os":"Mac 10.10","breakpointed":null,"browser":"ipad"},{"browser_short_version":"8.0","video_url":"https://saucelabs.com/jobs/fc7cab0c78cb4f20aa010055d760c0fe/video.flv","creation_time":1453169738,"custom-data":null,"browser_version":"8.0.","owner":"fcore","id":"fc7cab0c78cb4f20aa010055d760c0fe","record_screenshots":true,"record_video":true,"build":"04-infinite-scroll_103250746","passed":false,"public":"public","end_time":1453169813,"status":"complete","log_url":"https://saucelabs.com/jobs/fc7cab0c78cb4f20aa010055d760c0fe/selenium-server.log","start_time":1453169739,"proxied":true,"modification_time":1453169814,"tags":["103250746","f474ee7433ef972b13bfe27995acc773e8cdba91","fluxex"],"name":"FluxEx browser test for example: 04-infinite-scroll_103250746","commands_not_successful":4,"consolidated_status":"failed","assigned_tunnel_id":"333f633b417a42e48343b14d80caacc8","error":null,"os":"Mac 10.10","breakpointed":null,"browser":"iphone"}]}
