{"browsers":{"firefox":{"34":true},"chrome":{"35":true},"explorer":{"9":true,"10":true,"11":true},"safari":{"6":true,"7":true},"iphone":{"7.1":true,"6.1":true,"8.1":true,"8.0":true},"ipad":{"6.1":true,"7.1":true,"8.0":true,"8.1":true},"android-browser":{"4.4":true,"4.1":true,"4.0":true}},"raw":[{"browser_short_version":"9","video_url":"https://saucelabs.com/jobs/1bf4bc94ce5e4c6a94fa2ddad138f54e/video.flv","creation_time":1424851037,"custom-data":null,"browser_version":"9.0.8112.16421.","owner":"fcore","id":"1bf4bc94ce5e4c6a94fa2ddad138f54e","log_url":"https://saucelabs.com/jobs/1bf4bc94ce5e4c6a94fa2ddad138f54e/selenium-server.log","record_screenshots":true,"record_video":true,"build":"03-service_52097945","passed":true,"public":"public","status":"complete","tags":["52097945","db19683075b734bc0c8f3c5bc16bd7e6b2c75594","fluxex"],"start_time":1424851039,"proxied":true,"commands_not_successful":5,"name":"FluxEx browser test for example: 03-service_52097945","end_time":1424851056,"error":null,"os":"Windows 2008","breakpointed":null,"browser":"iexplore"},{"browser_short_version":"7.1","video_url":"https://saucelabs.com/jobs/2dd8b27355dd49358bc3a08e4f33bd3a/video.flv","creation_time":1424851037,"custom-data":null,"browser_version":"7.1.","owner":"fcore","id":"2dd8b27355dd49358bc3a08e4f33bd3a","log_url":"https://saucelabs.com/jobs/2dd8b27355dd49358bc3a08e4f33bd3a/selenium-server.log","record_screenshots":true,"record_video":true,"build":"03-service_52097945","passed":true,"public":"public","status":"complete","tags":["52097945","db19683075b734bc0c8f3c5bc16bd7e6b2c75594","fluxex"],"start_time":1424851039,"proxied":true,"commands_not_successful":5,"name":"FluxEx browser test for example: 03-service_52097945","end_time":1424851104,"error":null,"os":"Mac 10.9","breakpointed":null,"browser":"iphone"},{"browser_short_version":"7","video_url":"https://saucelabs.com/jobs/46cea3560129452393bcc5a2341711b9/video.flv","creation_time":1424851037,"custom-data":null,"browser_version":"7.0.","owner":"fcore","id":"46cea3560129452393bcc5a2341711b9","log_url":"https://saucelabs.com/jobs/46cea3560129452393bcc5a2341711b9/selenium-server.log","record_screenshots":true,"record_video":true,"build":"03-service_52097945","passed":true,"public":"public","status":"complete","tags":["52097945","db19683075b734bc0c8f3c5bc16bd7e6b2c75594","fluxex"],"start_time":1424851039,"proxied":true,"commands_not_successful":5,"name":"FluxEx browser test for example: 03-service_52097945","end_time":1424851057,"error":null,"os":"Mac 10.9","breakpointed":null,"browser":"safari"},{"browser_short_version":"6.1","video_url":"https://saucelabs.com/jobs/47dd49fbee5e4510829acd18b7950f8f/video.flv","creation_time":1424851037,"custom-data":null,"browser_version":"6.1.","owner":"fcore","id":"47dd49fbee5e4510829acd18b7950f8f","log_url":"https://saucelabs.com/jobs/47dd49fbee5e4510829acd18b7950f8f/selenium-server.log","record_screenshots":true,"record_video":true,"build":"03-service_52097945","passed":true,"public":"public","status":"complete","tags":["52097945","db19683075b734bc0c8f3c5bc16bd7e6b2c75594","fluxex"],"start_time":1424851039,"proxied":true,"commands_not_successful":6,"name":"FluxEx browser test for example: 03-service_52097945","end_time":1424851078,"error":null,"os":"Mac 10.8","breakpointed":null,"browser":"ipad"},{"browser_short_version":"7.1","video_url":"https://saucelabs.com/jobs/4da156c4b6364f8391151a99f4037b2f/video.flv","creation_time":1424851037,"custom-data":null,"browser_version":"7.1.","owner":"fcore","id":"4da156c4b6364f8391151a99f4037b2f","log_url":"https://saucelabs.com/jobs/4da156c4b6364f8391151a99f4037b2f/selenium-server.log","record_screenshots":true,"record_video":true,"build":"03-service_52097945","passed":true,"public":"public","status":"complete","tags":["52097945","db19683075b734bc0c8f3c5bc16bd7e6b2c75594","fluxex"],"start_time":1424851039,"proxied":true,"commands_not_successful":5,"name":"FluxEx browser test for example: 03-service_52097945","end_time":1424851095,"error":null,"os":"Mac 10.9","breakpointed":null,"browser":"ipad"},{"browser_short_version":"35","video_url":"https://saucelabs.com/jobs/68182555982a44bebe875677e579f56a/video.flv","creation_time":1424851037,"custom-data":null,"browser_version":"35.0.1916.153.","owner":"fcore","id":"68182555982a44bebe875677e579f56a","log_url":"https://saucelabs.com/jobs/68182555982a44bebe875677e579f56a/selenium-server.log","record_screenshots":true,"record_video":true,"build":"03-service_52097945","passed":true,"public":"public","status":"complete","tags":["52097945","db19683075b734bc0c8f3c5bc16bd7e6b2c75594","fluxex"],"start_time":1424851037,"proxied":true,"commands_not_successful":2,"name":"FluxEx browser test for example: 03-service_52097945","end_time":1424851047,"error":null,"os":"Linux","breakpointed":null,"browser":"googlechrome"},{"browser_short_version":"4.4","video_url":"https://saucelabs.com/jobs/70b76b5eeeb9409a9cc64590d24d11d0/video.flv","creation_time":1424851037,"custom-data":null,"browser_version":"4.4.","owner":"fcore","id":"70b76b5eeeb9409a9cc64590d24d11d0","log_url":"https://saucelabs.com/jobs/70b76b5eeeb9409a9cc64590d24d11d0/selenium-server.log","record_screenshots":true,"record_video":true,"build":"03-service_52097945","passed":true,"public":"public","status":"complete","tags":["52097945","db19683075b734bc0c8f3c5bc16bd7e6b2c75594","fluxex"],"start_time":1424851039,"proxied":true,"commands_not_successful":4,"name":"FluxEx browser test for example: 03-service_52097945","end_time":1424851093,"error":null,"os":"Linux","breakpointed":null,"browser":"android"},{"browser_short_version":"6.1","video_url":"https://saucelabs.com/jobs/7ef3c303aa8f4ea1809d18c5b73c1675/video.flv","creation_time":1424851037,"custom-data":null,"browser_version":"6.1.","owner":"fcore","id":"7ef3c303aa8f4ea1809d18c5b73c1675","log_url":"https://saucelabs.com/jobs/7ef3c303aa8f4ea1809d18c5b73c1675/selenium-server.log","record_screenshots":true,"record_video":true,"build":"03-service_52097945","passed":true,"public":"public","status":"complete","tags":["52097945","db19683075b734bc0c8f3c5bc16bd7e6b2c75594","fluxex"],"start_time":1424851039,"proxied":true,"commands_not_successful":6,"name":"FluxEx browser test for example: 03-service_52097945","end_time":1424851079,"error":null,"os":"Mac 10.8","breakpointed":null,"browser":"iphone"},{"browser_short_version":"8.0","video_url":"https://saucelabs.com/jobs/841a628813284a92a58ab6e111fc9c22/video.flv","creation_time":1424851037,"custom-data":null,"browser_version":"8.0.","owner":"fcore","id":"841a628813284a92a58ab6e111fc9c22","log_url":"https://saucelabs.com/jobs/841a628813284a92a58ab6e111fc9c22/selenium-server.log","record_screenshots":true,"record_video":true,"build":"03-service_52097945","passed":true,"public":"public","status":"complete","tags":["52097945","db19683075b734bc0c8f3c5bc16bd7e6b2c75594","fluxex"],"start_time":1424851039,"proxied":true,"commands_not_successful":5,"name":"FluxEx browser test for example: 03-service_52097945","end_time":1424851117,"error":null,"os":"Mac 10.10","breakpointed":null,"browser":"ipad"},{"browser_short_version":"4.1","video_url":"https://saucelabs.com/jobs/9edcb5c4b33b4382a1308fe9d09a0480/video.flv","creation_time":1424851037,"custom-data":null,"browser_version":"4.1.","owner":"fcore","id":"9edcb5c4b33b4382a1308fe9d09a0480","log_url":"https://saucelabs.com/jobs/9edcb5c4b33b4382a1308fe9d09a0480/selenium-server.log","record_screenshots":true,"record_video":true,"build":"03-service_52097945","passed":true,"public":"public","status":"complete","tags":["52097945","db19683075b734bc0c8f3c5bc16bd7e6b2c75594","fluxex"],"start_time":1424851039,"proxied":true,"commands_not_successful":4,"name":"FluxEx browser test for example: 03-service_52097945","end_time":1424851087,"error":null,"os":"Linux","breakpointed":null,"browser":"android"},{"browser_short_version":"8.1","video_url":"https://saucelabs.com/jobs/aadfb913fd1b4dde8cedad703b09aad9/video.flv","creation_time":1424851037,"custom-data":null,"browser_version":"8.1.","owner":"fcore","id":"aadfb913fd1b4dde8cedad703b09aad9","log_url":"https://saucelabs.com/jobs/aadfb913fd1b4dde8cedad703b09aad9/selenium-server.log","record_screenshots":true,"record_video":true,"build":"03-service_52097945","passed":true,"public":"public","status":"in progress","tags":["52097945","db19683075b734bc0c8f3c5bc16bd7e6b2c75594","fluxex"],"start_time":1424851039,"proxied":true,"commands_not_successful":0,"video_secret":"eca3cf5d934d4283b693edada8a4f021","name":"FluxEx browser test for example: 03-service_52097945","end_time":null,"error":null,"os":"Mac 10.10","breakpointed":null,"browser":"iphone"},{"browser_short_version":"11","video_url":"https://saucelabs.com/jobs/bbf9aa7168b24acbb0d4ccda4f60c24b/video.flv","creation_time":1424851037,"custom-data":null,"browser_version":"11.0.9600.17278.","owner":"fcore","id":"bbf9aa7168b24acbb0d4ccda4f60c24b","log_url":"https://saucelabs.com/jobs/bbf9aa7168b24acbb0d4ccda4f60c24b/selenium-server.log","record_screenshots":true,"record_video":true,"build":"03-service_52097945","passed":true,"public":"public","status":"complete","tags":["52097945","db19683075b734bc0c8f3c5bc16bd7e6b2c75594","fluxex"],"start_time":1424851039,"proxied":true,"commands_not_successful":5,"name":"FluxEx browser test for example: 03-service_52097945","end_time":1424851052,"error":null,"os":"Windows 2012 R2","breakpointed":null,"browser":"iexplore"},{"browser_short_version":"8.1","video_url":"https://saucelabs.com/jobs/d61352e159f94864a77b2c2a5247e121/video.flv","creation_time":1424851037,"custom-data":null,"browser_version":"8.1.","owner":"fcore","id":"d61352e159f94864a77b2c2a5247e121","log_url":"https://saucelabs.com/jobs/d61352e159f94864a77b2c2a5247e121/selenium-server.log","record_screenshots":true,"record_video":true,"build":"03-service_52097945","passed":true,"public":"public","status":"complete","tags":["52097945","db19683075b734bc0c8f3c5bc16bd7e6b2c75594","fluxex"],"start_time":1424851039,"proxied":true,"commands_not_successful":5,"name":"FluxEx browser test for example: 03-service_52097945","end_time":1424851119,"error":null,"os":"Mac 10.10","breakpointed":null,"browser":"ipad"},{"browser_short_version":"34","video_url":"https://saucelabs.com/jobs/d6d9e1cd207b4e579b6df40e12c76cc7/video.flv","creation_time":1424851037,"custom-data":null,"browser_version":"34.0.","owner":"fcore","id":"d6d9e1cd207b4e579b6df40e12c76cc7","log_url":"https://saucelabs.com/jobs/d6d9e1cd207b4e579b6df40e12c76cc7/selenium-server.log","record_screenshots":true,"record_video":true,"build":"03-service_52097945","passed":true,"public":"public","status":"complete","tags":["52097945","db19683075b734bc0c8f3c5bc16bd7e6b2c75594","fluxex"],"start_time":1424851039,"proxied":true,"commands_not_successful":2,"name":"FluxEx browser test for example: 03-service_52097945","end_time":1424851053,"error":null,"os":"Linux","breakpointed":null,"browser":"firefox"},{"browser_short_version":"4.0","video_url":"https://saucelabs.com/jobs/e4b4c5ac70524f81af92e0b1d1a815df/video.flv","creation_time":1424851037,"custom-data":null,"browser_version":"4.0.4.","owner":"fcore","id":"e4b4c5ac70524f81af92e0b1d1a815df","log_url":"https://saucelabs.com/jobs/e4b4c5ac70524f81af92e0b1d1a815df/selenium-server.log","record_screenshots":true,"record_video":true,"build":"03-service_52097945","passed":true,"public":"public","status":"complete","tags":["52097945","db19683075b734bc0c8f3c5bc16bd7e6b2c75594","fluxex"],"start_time":1424851039,"proxied":true,"commands_not_successful":4,"name":"FluxEx browser test for example: 03-service_52097945","end_time":1424851084,"error":null,"os":"Linux","breakpointed":null,"browser":"android"},{"browser_short_version":"10","video_url":"https://saucelabs.com/jobs/ebe987d82af7492ab550da6020dd855f/video.flv","creation_time":1424851037,"custom-data":null,"browser_version":"10.0.9200.16580.","owner":"fcore","id":"ebe987d82af7492ab550da6020dd855f","log_url":"https://saucelabs.com/jobs/ebe987d82af7492ab550da6020dd855f/selenium-server.log","record_screenshots":true,"record_video":true,"build":"03-service_52097945","passed":true,"public":"public","status":"complete","tags":["52097945","db19683075b734bc0c8f3c5bc16bd7e6b2c75594","fluxex"],"start_time":1424851039,"proxied":true,"commands_not_successful":5,"name":"FluxEx browser test for example: 03-service_52097945","end_time":1424851055,"error":null,"os":"Windows 2012","breakpointed":null,"browser":"iexplore"},{"browser_short_version":"8.0","video_url":"https://saucelabs.com/jobs/f03745beb14d4c11bb56b92a84cea452/video.flv","creation_time":1424851037,"custom-data":null,"browser_version":"8.0.","owner":"fcore","id":"f03745beb14d4c11bb56b92a84cea452","log_url":"https://saucelabs.com/jobs/f03745beb14d4c11bb56b92a84cea452/selenium-server.log","record_screenshots":true,"record_video":true,"build":"03-service_52097945","passed":true,"public":"public","status":"complete","tags":["52097945","db19683075b734bc0c8f3c5bc16bd7e6b2c75594","fluxex"],"start_time":1424851039,"proxied":true,"commands_not_successful":5,"name":"FluxEx browser test for example: 03-service_52097945","end_time":1424851118,"error":null,"os":"Mac 10.10","breakpointed":null,"browser":"iphone"},{"browser_short_version":"6","video_url":"https://saucelabs.com/jobs/fef16aa7119040f6ac95fa460670fa18/video.flv","creation_time":1424851037,"custom-data":null,"browser_version":"6.0.4.","owner":"fcore","id":"fef16aa7119040f6ac95fa460670fa18","log_url":"https://saucelabs.com/jobs/fef16aa7119040f6ac95fa460670fa18/selenium-server.log","record_screenshots":true,"record_video":true,"build":"03-service_52097945","passed":true,"public":"public","status":"complete","tags":["52097945","db19683075b734bc0c8f3c5bc16bd7e6b2c75594","fluxex"],"start_time":1424851039,"proxied":true,"commands_not_successful":5,"name":"FluxEx browser test for example: 03-service_52097945","end_time":1424851052,"error":null,"os":"Mac 10.8","breakpointed":null,"browser":"safari"},{"browser_short_version":"9","video_url":"https://saucelabs.com/jobs/0846f6938ef34167b787aac93276e60b/video.flv","creation_time":1424850865,"custom-data":null,"browser_version":"9.0.8112.16421.","owner":"fcore","id":"0846f6938ef34167b787aac93276e60b","log_url":"https://saucelabs.com/jobs/0846f6938ef34167b787aac93276e60b/selenium-server.log","record_screenshots":true,"record_video":true,"build":"02-routing_52097945","passed":false,"public":"public","status":"complete","tags":["52097945","db19683075b734bc0c8f3c5bc16bd7e6b2c75594","fluxex"],"start_time":1424850867,"proxied":true,"commands_not_successful":67,"name":"FluxEx browser test for example: 02-routing_52097945","end_time":1424850913,"error":null,"os":"Windows 2008","breakpointed":null,"browser":"iexplore"},{"browser_short_version":"11","video_url":"https://saucelabs.com/jobs/0cbb6f393c4943c39a725a4dafef0384/video.flv","creation_time":1424850865,"custom-data":null,"browser_version":"11.0.9600.17278.","owner":"fcore","id":"0cbb6f393c4943c39a725a4dafef0384","log_url":"https://saucelabs.com/jobs/0cbb6f393c4943c39a725a4dafef0384/selenium-server.log","record_screenshots":true,"record_video":true,"build":"02-routing_52097945","passed":true,"public":"public","status":"complete","tags":["52097945","db19683075b734bc0c8f3c5bc16bd7e6b2c75594","fluxex"],"start_time":1424850866,"proxied":true,"commands_not_successful":9,"name":"FluxEx browser test for example: 02-routing_52097945","end_time":1424850885,"error":null,"os":"Windows 2012 R2","breakpointed":null,"browser":"iexplore"},{"browser_short_version":"4.1","video_url":"https://saucelabs.com/jobs/342a7058f572420eb4fb3426516b7c45/video.flv","creation_time":1424850865,"custom-data":null,"browser_version":"4.1.","owner":"fcore","id":"342a7058f572420eb4fb3426516b7c45","log_url":"https://saucelabs.com/jobs/342a7058f572420eb4fb3426516b7c45/selenium-server.log","record_screenshots":true,"record_video":true,"build":"02-routing_52097945","passed":true,"public":"public","status":"complete","tags":["52097945","db19683075b734bc0c8f3c5bc16bd7e6b2c75594","fluxex"],"start_time":1424850867,"proxied":true,"commands_not_successful":8,"name":"FluxEx browser test for example: 02-routing_52097945","end_time":1424850920,"error":null,"os":"Linux","breakpointed":null,"browser":"android"},{"browser_short_version":"7.1","video_url":"https://saucelabs.com/jobs/4686f5a23e354b05b57ffdc7cba73b9b/video.flv","creation_time":1424850865,"custom-data":null,"browser_version":"7.1.","owner":"fcore","id":"4686f5a23e354b05b57ffdc7cba73b9b","log_url":"https://saucelabs.com/jobs/4686f5a23e354b05b57ffdc7cba73b9b/selenium-server.log","record_screenshots":true,"record_video":true,"build":"02-routing_52097945","passed":true,"public":"public","status":"complete","tags":["52097945","db19683075b734bc0c8f3c5bc16bd7e6b2c75594","fluxex"],"start_time":1424850867,"proxied":true,"commands_not_successful":8,"name":"FluxEx browser test for example: 02-routing_52097945","end_time":1424850960,"error":null,"os":"Mac 10.9","breakpointed":null,"browser":"iphone"},{"browser_short_version":"6","video_url":"https://saucelabs.com/jobs/5db2bdb871dd4477ac70b3aac0a0946a/video.flv","creation_time":1424850865,"custom-data":null,"browser_version":"6.0.4.","owner":"fcore","id":"5db2bdb871dd4477ac70b3aac0a0946a","log_url":"https://saucelabs.com/jobs/5db2bdb871dd4477ac70b3aac0a0946a/selenium-server.log","record_screenshots":true,"record_video":true,"build":"02-routing_52097945","passed":true,"public":"public","status":"complete","tags":["52097945","db19683075b734bc0c8f3c5bc16bd7e6b2c75594","fluxex"],"start_time":1424850866,"proxied":true,"commands_not_successful":9,"name":"FluxEx browser test for example: 02-routing_52097945","end_time":1424850887,"error":null,"os":"Mac 10.8","breakpointed":null,"browser":"safari"},{"browser_short_version":"4.0","video_url":"https://saucelabs.com/jobs/6513a6de69a6424ea7aafcf9fdbbc850/video.flv","creation_time":1424850865,"custom-data":null,"browser_version":"4.0.4.","owner":"fcore","id":"6513a6de69a6424ea7aafcf9fdbbc850","log_url":"https://saucelabs.com/jobs/6513a6de69a6424ea7aafcf9fdbbc850/selenium-server.log","record_screenshots":true,"record_video":true,"build":"02-routing_52097945","passed":true,"public":"public","status":"complete","tags":["52097945","db19683075b734bc0c8f3c5bc16bd7e6b2c75594","fluxex"],"start_time":1424850867,"proxied":true,"commands_not_successful":8,"name":"FluxEx browser test for example: 02-routing_52097945","end_time":1424850922,"error":null,"os":"Linux","breakpointed":null,"browser":"android"},{"browser_short_version":"8.1","video_url":"https://saucelabs.com/jobs/68dd3cf854c2491bbfd9be642f017b93/video.flv","creation_time":1424850865,"custom-data":null,"browser_version":"8.1.","owner":"fcore","id":"68dd3cf854c2491bbfd9be642f017b93","log_url":"https://saucelabs.com/jobs/68dd3cf854c2491bbfd9be642f017b93/selenium-server.log","record_screenshots":true,"record_video":true,"build":"02-routing_52097945","passed":true,"public":"public","status":"complete","tags":["52097945","db19683075b734bc0c8f3c5bc16bd7e6b2c75594","fluxex"],"start_time":1424850866,"proxied":true,"commands_not_successful":8,"name":"FluxEx browser test for example: 02-routing_52097945","end_time":1424850963,"error":null,"os":"Mac 10.10","breakpointed":null,"browser":"iphone"},{"browser_short_version":"34","video_url":"https://saucelabs.com/jobs/79da36c0de5e4db4ac306c03321ae9ed/video.flv","creation_time":1424850865,"custom-data":null,"browser_version":"34.0.","owner":"fcore","id":"79da36c0de5e4db4ac306c03321ae9ed","log_url":"https://saucelabs.com/jobs/79da36c0de5e4db4ac306c03321ae9ed/selenium-server.log","record_screenshots":true,"record_video":true,"build":"02-routing_52097945","passed":true,"public":"public","status":"complete","tags":["52097945","db19683075b734bc0c8f3c5bc16bd7e6b2c75594","fluxex"],"start_time":1424850867,"proxied":true,"commands_not_successful":4,"name":"FluxEx browser test for example: 02-routing_52097945","end_time":1424850886,"error":null,"os":"Linux","breakpointed":null,"browser":"firefox"},{"browser_short_version":"8.0","video_url":"https://saucelabs.com/jobs/7de21cd71d7543b195ccba1470d18fd2/video.flv","creation_time":1424850865,"custom-data":null,"browser_version":"8.0.","owner":"fcore","id":"7de21cd71d7543b195ccba1470d18fd2","log_url":"https://saucelabs.com/jobs/7de21cd71d7543b195ccba1470d18fd2/selenium-server.log","record_screenshots":true,"record_video":true,"build":"02-routing_52097945","passed":true,"public":"public","status":"complete","tags":["52097945","db19683075b734bc0c8f3c5bc16bd7e6b2c75594","fluxex"],"start_time":1424850867,"proxied":true,"commands_not_successful":8,"name":"FluxEx browser test for example: 02-routing_52097945","end_time":1424850974,"error":null,"os":"Mac 10.10","breakpointed":null,"browser":"iphone"},{"browser_short_version":"7.1","video_url":"https://saucelabs.com/jobs/8ae09c9004ec4269a0461c2701ffe8f9/video.flv","creation_time":1424850865,"custom-data":null,"browser_version":"7.1.","owner":"fcore","id":"8ae09c9004ec4269a0461c2701ffe8f9","log_url":"https://saucelabs.com/jobs/8ae09c9004ec4269a0461c2701ffe8f9/selenium-server.log","record_screenshots":true,"record_video":true,"build":"02-routing_52097945","passed":true,"public":"public","status":"complete","tags":["52097945","db19683075b734bc0c8f3c5bc16bd7e6b2c75594","fluxex"],"start_time":1424850867,"proxied":true,"commands_not_successful":8,"name":"FluxEx browser test for example: 02-routing_52097945","end_time":1424850948,"error":null,"os":"Mac 10.9","breakpointed":null,"browser":"ipad"},{"browser_short_version":"4.4","video_url":"https://saucelabs.com/jobs/8d187ec4f89341fbacb615741f0607a4/video.flv","creation_time":1424850865,"custom-data":null,"browser_version":"4.4.","owner":"fcore","id":"8d187ec4f89341fbacb615741f0607a4","log_url":"https://saucelabs.com/jobs/8d187ec4f89341fbacb615741f0607a4/selenium-server.log","record_screenshots":true,"record_video":true,"build":"02-routing_52097945","passed":true,"public":"public","status":"complete","tags":["52097945","db19683075b734bc0c8f3c5bc16bd7e6b2c75594","fluxex"],"start_time":1424850866,"proxied":true,"commands_not_successful":8,"name":"FluxEx browser test for example: 02-routing_52097945","end_time":1424850932,"error":null,"os":"Linux","breakpointed":null,"browser":"android"},{"browser_short_version":"6.1","video_url":"https://saucelabs.com/jobs/99611bc398d040818d27c09c76a9022c/video.flv","creation_time":1424850865,"custom-data":null,"browser_version":"6.1.","owner":"fcore","id":"99611bc398d040818d27c09c76a9022c","log_url":"https://saucelabs.com/jobs/99611bc398d040818d27c09c76a9022c/selenium-server.log","record_screenshots":true,"record_video":true,"build":"02-routing_52097945","passed":true,"public":"public","status":"complete","tags":["52097945","db19683075b734bc0c8f3c5bc16bd7e6b2c75594","fluxex"],"start_time":1424850867,"proxied":true,"commands_not_successful":10,"name":"FluxEx browser test for example: 02-routing_52097945","end_time":1424850919,"error":null,"os":"Mac 10.8","breakpointed":null,"browser":"iphone"},{"browser_short_version":"7","video_url":"https://saucelabs.com/jobs/9ede9a9836084f6f985b75ddd9bb10ff/video.flv","creation_time":1424850865,"custom-data":null,"browser_version":"7.0.","owner":"fcore","id":"9ede9a9836084f6f985b75ddd9bb10ff","log_url":"https://saucelabs.com/jobs/9ede9a9836084f6f985b75ddd9bb10ff/selenium-server.log","record_screenshots":true,"record_video":true,"build":"02-routing_52097945","passed":true,"public":"public","status":"complete","tags":["52097945","db19683075b734bc0c8f3c5bc16bd7e6b2c75594","fluxex"],"start_time":1424850867,"proxied":true,"commands_not_successful":9,"name":"FluxEx browser test for example: 02-routing_52097945","end_time":1424850884,"error":null,"os":"Mac 10.9","breakpointed":null,"browser":"safari"},{"browser_short_version":"8.1","video_url":"https://saucelabs.com/jobs/b8f862a95da0493aac5e77a524eeb366/video.flv","creation_time":1424850865,"custom-data":null,"browser_version":"8.1.","owner":"fcore","id":"b8f862a95da0493aac5e77a524eeb366","log_url":"https://saucelabs.com/jobs/b8f862a95da0493aac5e77a524eeb366/selenium-server.log","record_screenshots":true,"record_video":true,"build":"02-routing_52097945","passed":true,"public":"public","status":"complete","tags":["52097945","db19683075b734bc0c8f3c5bc16bd7e6b2c75594","fluxex"],"start_time":1424850867,"proxied":true,"commands_not_successful":8,"name":"FluxEx browser test for example: 02-routing_52097945","end_time":1424850966,"error":null,"os":"Mac 10.10","breakpointed":null,"browser":"ipad"},{"browser_short_version":"35","video_url":"https://saucelabs.com/jobs/ba3ee1a0285f4af78567ebc093ddac9a/video.flv","creation_time":1424850865,"custom-data":null,"browser_version":"35.0.1916.153.","owner":"fcore","id":"ba3ee1a0285f4af78567ebc093ddac9a","log_url":"https://saucelabs.com/jobs/ba3ee1a0285f4af78567ebc093ddac9a/selenium-server.log","record_screenshots":true,"record_video":true,"build":"02-routing_52097945","passed":true,"public":"public","status":"complete","tags":["52097945","db19683075b734bc0c8f3c5bc16bd7e6b2c75594","fluxex"],"start_time":1424850867,"proxied":true,"commands_not_successful":4,"name":"FluxEx browser test for example: 02-routing_52097945","end_time":1424850886,"error":null,"os":"Linux","breakpointed":null,"browser":"googlechrome"},{"browser_short_version":"8.0","video_url":"https://saucelabs.com/jobs/bd04d565826f4575b913a29cdce6c421/video.flv","creation_time":1424850865,"custom-data":null,"browser_version":"8.0.","owner":"fcore","id":"bd04d565826f4575b913a29cdce6c421","log_url":"https://saucelabs.com/jobs/bd04d565826f4575b913a29cdce6c421/selenium-server.log","record_screenshots":true,"record_video":true,"build":"02-routing_52097945","passed":true,"public":"public","status":"complete","tags":["52097945","db19683075b734bc0c8f3c5bc16bd7e6b2c75594","fluxex"],"start_time":1424850867,"proxied":true,"commands_not_successful":8,"name":"FluxEx browser test for example: 02-routing_52097945","end_time":1424850966,"error":null,"os":"Mac 10.10","breakpointed":null,"browser":"ipad"},{"browser_short_version":"6.1","video_url":"https://saucelabs.com/jobs/d91cf24a32064560b86cf292c40f2dab/video.flv","creation_time":1424850865,"custom-data":null,"browser_version":"6.1.","owner":"fcore","id":"d91cf24a32064560b86cf292c40f2dab","log_url":"https://saucelabs.com/jobs/d91cf24a32064560b86cf292c40f2dab/selenium-server.log","record_screenshots":true,"record_video":true,"build":"02-routing_52097945","passed":true,"public":"public","status":"complete","tags":["52097945","db19683075b734bc0c8f3c5bc16bd7e6b2c75594","fluxex"],"start_time":1424850867,"proxied":true,"commands_not_successful":10,"name":"FluxEx browser test for example: 02-routing_52097945","end_time":1424850912,"error":null,"os":"Mac 10.8","breakpointed":null,"browser":"ipad"},{"browser_short_version":"10","video_url":"https://saucelabs.com/jobs/f3df658d0a974d7a9207660939a0cb01/video.flv","creation_time":1424850865,"custom-data":null,"browser_version":"10.0.9200.16580.","owner":"fcore","id":"f3df658d0a974d7a9207660939a0cb01","log_url":"https://saucelabs.com/jobs/f3df658d0a974d7a9207660939a0cb01/selenium-server.log","record_screenshots":true,"record_video":true,"build":"02-routing_52097945","passed":true,"public":"public","status":"complete","tags":["52097945","db19683075b734bc0c8f3c5bc16bd7e6b2c75594","fluxex"],"start_time":1424850866,"proxied":true,"commands_not_successful":9,"name":"FluxEx browser test for example: 02-routing_52097945","end_time":1424850890,"error":null,"os":"Windows 2012","breakpointed":null,"browser":"iexplore"},{"browser_short_version":"7.1","video_url":"https://saucelabs.com/jobs/b3a04df74fe3448a94d3908f49973973/video.flv","creation_time":1424850438,"custom-data":null,"browser_version":"7.1.","owner":"fcore","id":"b3a04df74fe3448a94d3908f49973973","log_url":"https://saucelabs.com/jobs/b3a04df74fe3448a94d3908f49973973/selenium-server.log","record_screenshots":true,"record_video":true,"build":"01-history-api_52097945","passed":true,"public":"public","status":"complete","tags":["52097945","db19683075b734bc0c8f3c5bc16bd7e6b2c75594","fluxex"],"start_time":1424850442,"proxied":true,"commands_not_successful":8,"name":"FluxEx browser test for example: 01-history-api_52097945","end_time":1424850522,"error":null,"os":"Mac 10.9","breakpointed":null,"browser":"ipad"},{"browser_short_version":"8.0","video_url":"https://saucelabs.com/jobs/cdee5e785446469481eb29595575501b/video.flv","creation_time":1424850438,"custom-data":null,"browser_version":"8.0.","owner":"fcore","id":"cdee5e785446469481eb29595575501b","log_url":"https://saucelabs.com/jobs/cdee5e785446469481eb29595575501b/selenium-server.log","record_screenshots":true,"record_video":true,"build":"01-history-api_52097945","passed":true,"public":"public","status":"complete","tags":["52097945","db19683075b734bc0c8f3c5bc16bd7e6b2c75594","fluxex"],"start_time":1424850442,"proxied":true,"commands_not_successful":8,"name":"FluxEx browser test for example: 01-history-api_52097945","end_time":1424850529,"error":null,"os":"Mac 10.10","breakpointed":null,"browser":"ipad"},{"browser_short_version":"11","video_url":"https://saucelabs.com/jobs/0c22a7838a71407f96ceb7d8d48a87cf/video.flv","creation_time":1424850437,"custom-data":null,"browser_version":"11.0.9600.17278.","owner":"fcore","id":"0c22a7838a71407f96ceb7d8d48a87cf","log_url":"https://saucelabs.com/jobs/0c22a7838a71407f96ceb7d8d48a87cf/selenium-server.log","record_screenshots":true,"record_video":true,"build":"01-history-api_52097945","passed":true,"public":"public","status":"complete","tags":["52097945","db19683075b734bc0c8f3c5bc16bd7e6b2c75594","fluxex"],"start_time":1424850439,"proxied":true,"commands_not_successful":9,"name":"FluxEx browser test for example: 01-history-api_52097945","end_time":1424850454,"error":null,"os":"Windows 2012 R2","breakpointed":null,"browser":"iexplore"},{"browser_short_version":"7.1","video_url":"https://saucelabs.com/jobs/1878716a5cbd45799f9af1523cacec24/video.flv","creation_time":1424850437,"custom-data":null,"browser_version":"7.1.","owner":"fcore","id":"1878716a5cbd45799f9af1523cacec24","log_url":"https://saucelabs.com/jobs/1878716a5cbd45799f9af1523cacec24/selenium-server.log","record_screenshots":true,"record_video":true,"build":"01-history-api_52097945","passed":true,"public":"public","status":"complete","tags":["52097945","db19683075b734bc0c8f3c5bc16bd7e6b2c75594","fluxex"],"start_time":1424850442,"proxied":true,"commands_not_successful":8,"name":"FluxEx browser test for example: 01-history-api_52097945","end_time":1424850521,"error":null,"os":"Mac 10.9","breakpointed":null,"browser":"iphone"},{"browser_short_version":"7","video_url":"https://saucelabs.com/jobs/5f52edd3b0a54beca0a32ba8488af99c/video.flv","creation_time":1424850437,"custom-data":null,"browser_version":"7.0.","owner":"fcore","id":"5f52edd3b0a54beca0a32ba8488af99c","log_url":"https://saucelabs.com/jobs/5f52edd3b0a54beca0a32ba8488af99c/selenium-server.log","record_screenshots":true,"record_video":true,"build":"01-history-api_52097945","passed":true,"public":"public","status":"complete","tags":["52097945","db19683075b734bc0c8f3c5bc16bd7e6b2c75594","fluxex"],"start_time":1424850438,"proxied":true,"commands_not_successful":9,"name":"FluxEx browser test for example: 01-history-api_52097945","end_time":1424850456,"error":null,"os":"Mac 10.9","breakpointed":null,"browser":"safari"},{"browser_short_version":"35","video_url":"https://saucelabs.com/jobs/701e7f9b96c84ef6b3d1d87bb50b723a/video.flv","creation_time":1424850437,"custom-data":null,"browser_version":"35.0.1916.153.","owner":"fcore","id":"701e7f9b96c84ef6b3d1d87bb50b723a","log_url":"https://saucelabs.com/jobs/701e7f9b96c84ef6b3d1d87bb50b723a/selenium-server.log","record_screenshots":true,"record_video":true,"build":"01-history-api_52097945","passed":true,"public":"public","status":"complete","tags":["52097945","db19683075b734bc0c8f3c5bc16bd7e6b2c75594","fluxex"],"start_time":1424850442,"proxied":true,"commands_not_successful":4,"name":"FluxEx browser test for example: 01-history-api_52097945","end_time":1424850458,"error":null,"os":"Linux","breakpointed":null,"browser":"googlechrome"},{"browser_short_version":"34","video_url":"https://saucelabs.com/jobs/7f51eb249d824437b186972a7a3fc6b4/video.flv","creation_time":1424850437,"custom-data":null,"browser_version":"34.0.","owner":"fcore","id":"7f51eb249d824437b186972a7a3fc6b4","log_url":"https://saucelabs.com/jobs/7f51eb249d824437b186972a7a3fc6b4/selenium-server.log","record_screenshots":true,"record_video":true,"build":"01-history-api_52097945","passed":true,"public":"public","status":"complete","tags":["52097945","db19683075b734bc0c8f3c5bc16bd7e6b2c75594","fluxex"],"start_time":1424850442,"proxied":true,"commands_not_successful":4,"name":"FluxEx browser test for example: 01-history-api_52097945","end_time":1424850458,"error":null,"os":"Linux","breakpointed":null,"browser":"firefox"},{"browser_short_version":"4.0","video_url":"https://saucelabs.com/jobs/8bb698f2dda24209857121da1d9ffcec/video.flv","creation_time":1424850437,"custom-data":null,"browser_version":"4.0.4.","owner":"fcore","id":"8bb698f2dda24209857121da1d9ffcec","log_url":"https://saucelabs.com/jobs/8bb698f2dda24209857121da1d9ffcec/selenium-server.log","record_screenshots":true,"record_video":true,"build":"01-history-api_52097945","passed":true,"public":"public","status":"complete","tags":["52097945","db19683075b734bc0c8f3c5bc16bd7e6b2c75594","fluxex"],"start_time":1424850442,"proxied":true,"commands_not_successful":8,"name":"FluxEx browser test for example: 01-history-api_52097945","end_time":1424850496,"error":null,"os":"Linux","breakpointed":null,"browser":"android"},{"browser_short_version":"8.1","video_url":"https://saucelabs.com/jobs/908a2b900fbb40558fdf11c3e55433f8/video.flv","creation_time":1424850437,"custom-data":null,"browser_version":"8.1.","owner":"fcore","id":"908a2b900fbb40558fdf11c3e55433f8","log_url":"https://saucelabs.com/jobs/908a2b900fbb40558fdf11c3e55433f8/selenium-server.log","record_screenshots":true,"record_video":true,"build":"01-history-api_52097945","passed":true,"public":"public","status":"complete","tags":["52097945","db19683075b734bc0c8f3c5bc16bd7e6b2c75594","fluxex"],"start_time":1424850442,"proxied":true,"commands_not_successful":8,"name":"FluxEx browser test for example: 01-history-api_52097945","end_time":1424850540,"error":null,"os":"Mac 10.10","breakpointed":null,"browser":"iphone"},{"browser_short_version":"6","video_url":"https://saucelabs.com/jobs/a01ea2413c4744089408e94d29dd9db5/video.flv","creation_time":1424850437,"custom-data":null,"browser_version":"6.0.4.","owner":"fcore","id":"a01ea2413c4744089408e94d29dd9db5","log_url":"https://saucelabs.com/jobs/a01ea2413c4744089408e94d29dd9db5/selenium-server.log","record_screenshots":true,"record_video":true,"build":"01-history-api_52097945","passed":true,"public":"public","status":"complete","tags":["52097945","db19683075b734bc0c8f3c5bc16bd7e6b2c75594","fluxex"],"start_time":1424850442,"proxied":true,"commands_not_successful":9,"name":"FluxEx browser test for example: 01-history-api_52097945","end_time":1424850460,"error":null,"os":"Mac 10.8","breakpointed":null,"browser":"safari"},{"browser_short_version":"6.1","video_url":"https://saucelabs.com/jobs/a256800c43244d4da27ec2fab208a1aa/video.flv","creation_time":1424850437,"custom-data":null,"browser_version":"6.1.","owner":"fcore","id":"a256800c43244d4da27ec2fab208a1aa","log_url":"https://saucelabs.com/jobs/a256800c43244d4da27ec2fab208a1aa/selenium-server.log","record_screenshots":true,"record_video":true,"build":"01-history-api_52097945","passed":true,"public":"public","status":"complete","tags":["52097945","db19683075b734bc0c8f3c5bc16bd7e6b2c75594","fluxex"],"start_time":1424850442,"proxied":true,"commands_not_successful":10,"name":"FluxEx browser test for example: 01-history-api_52097945","end_time":1424850490,"error":null,"os":"Mac 10.8","breakpointed":null,"browser":"ipad"},{"browser_short_version":"4.4","video_url":"https://saucelabs.com/jobs/ace1c6d701c545f88456004dac383e74/video.flv","creation_time":1424850437,"custom-data":null,"browser_version":"4.4.","owner":"fcore","id":"ace1c6d701c545f88456004dac383e74","log_url":"https://saucelabs.com/jobs/ace1c6d701c545f88456004dac383e74/selenium-server.log","record_screenshots":true,"record_video":true,"build":"01-history-api_52097945","passed":true,"public":"public","status":"complete","tags":["52097945","db19683075b734bc0c8f3c5bc16bd7e6b2c75594","fluxex"],"start_time":1424850439,"proxied":true,"commands_not_successful":8,"name":"FluxEx browser test for example: 01-history-api_52097945","end_time":1424850504,"error":null,"os":"Linux","breakpointed":null,"browser":"android"},{"browser_short_version":"6.1","video_url":"https://saucelabs.com/jobs/bd6a3094c78348cfb593aec11f1931b2/video.flv","creation_time":1424850437,"custom-data":null,"browser_version":"6.1.","owner":"fcore","id":"bd6a3094c78348cfb593aec11f1931b2","log_url":"https://saucelabs.com/jobs/bd6a3094c78348cfb593aec11f1931b2/selenium-server.log","record_screenshots":true,"record_video":true,"build":"01-history-api_52097945","passed":true,"public":"public","status":"complete","tags":["52097945","db19683075b734bc0c8f3c5bc16bd7e6b2c75594","fluxex"],"start_time":1424850442,"proxied":true,"commands_not_successful":10,"name":"FluxEx browser test for example: 01-history-api_52097945","end_time":1424850480,"error":null,"os":"Mac 10.8","breakpointed":null,"browser":"iphone"},{"browser_short_version":"4.1","video_url":"https://saucelabs.com/jobs/c4ab090aff28491c982d5a3fb09b833f/video.flv","creation_time":1424850437,"custom-data":null,"browser_version":"4.1.","owner":"fcore","id":"c4ab090aff28491c982d5a3fb09b833f","log_url":"https://saucelabs.com/jobs/c4ab090aff28491c982d5a3fb09b833f/selenium-server.log","record_screenshots":true,"record_video":true,"build":"01-history-api_52097945","passed":true,"public":"public","status":"complete","tags":["52097945","db19683075b734bc0c8f3c5bc16bd7e6b2c75594","fluxex"],"start_time":1424850442,"proxied":true,"commands_not_successful":8,"name":"FluxEx browser test for example: 01-history-api_52097945","end_time":1424850496,"error":null,"os":"Linux","breakpointed":null,"browser":"android"},{"browser_short_version":"8.0","video_url":"https://saucelabs.com/jobs/c65c3bed7ade41108d6d22ca41e77872/video.flv","creation_time":1424850437,"custom-data":null,"browser_version":"8.0.","owner":"fcore","id":"c65c3bed7ade41108d6d22ca41e77872","log_url":"https://saucelabs.com/jobs/c65c3bed7ade41108d6d22ca41e77872/selenium-server.log","record_screenshots":true,"record_video":true,"build":"01-history-api_52097945","passed":true,"public":"public","status":"complete","tags":["52097945","db19683075b734bc0c8f3c5bc16bd7e6b2c75594","fluxex"],"start_time":1424850442,"proxied":true,"commands_not_successful":8,"name":"FluxEx browser test for example: 01-history-api_52097945","end_time":1424850528,"error":null,"os":"Mac 10.10","breakpointed":null,"browser":"iphone"},{"browser_short_version":"10","video_url":"https://saucelabs.com/jobs/c70f3fc686364cbd9c7cf63fa22d820b/video.flv","creation_time":1424850437,"custom-data":null,"browser_version":"10.0.9200.16580.","owner":"fcore","id":"c70f3fc686364cbd9c7cf63fa22d820b","log_url":"https://saucelabs.com/jobs/c70f3fc686364cbd9c7cf63fa22d820b/selenium-server.log","record_screenshots":true,"record_video":true,"build":"01-history-api_52097945","passed":true,"public":"public","status":"complete","tags":["52097945","db19683075b734bc0c8f3c5bc16bd7e6b2c75594","fluxex"],"start_time":1424850442,"proxied":true,"commands_not_successful":9,"name":"FluxEx browser test for example: 01-history-api_52097945","end_time":1424850458,"error":null,"os":"Windows 2012","breakpointed":null,"browser":"iexplore"},{"browser_short_version":"8.1","video_url":"https://saucelabs.com/jobs/cb749abc06414bc9af3571e0a2fca65b/video.flv","creation_time":1424850437,"custom-data":null,"browser_version":"8.1.","owner":"fcore","id":"cb749abc06414bc9af3571e0a2fca65b","log_url":"https://saucelabs.com/jobs/cb749abc06414bc9af3571e0a2fca65b/selenium-server.log","record_screenshots":true,"record_video":true,"build":"01-history-api_52097945","passed":true,"public":"public","status":"complete","tags":["52097945","db19683075b734bc0c8f3c5bc16bd7e6b2c75594","fluxex"],"start_time":1424850715,"proxied":true,"commands_not_successful":8,"name":"FluxEx browser test for example: 01-history-api_52097945","end_time":1424850803,"error":null,"os":"Mac 10.10","breakpointed":null,"browser":"ipad"},{"browser_short_version":"9","video_url":"https://saucelabs.com/jobs/ce3c6eb47eee422493b3b75de18f3638/video.flv","creation_time":1424850437,"custom-data":null,"browser_version":"9.0.8112.16421.","owner":"fcore","id":"ce3c6eb47eee422493b3b75de18f3638","log_url":"https://saucelabs.com/jobs/ce3c6eb47eee422493b3b75de18f3638/selenium-server.log","record_screenshots":true,"record_video":true,"build":"01-history-api_52097945","passed":false,"public":"public","status":"complete","tags":["52097945","db19683075b734bc0c8f3c5bc16bd7e6b2c75594","fluxex"],"start_time":1424850442,"proxied":true,"commands_not_successful":91,"name":"FluxEx browser test for example: 01-history-api_52097945","end_time":1424850488,"error":null,"os":"Windows 2008","breakpointed":null,"browser":"iexplore"},{"browser_short_version":"6.1","video_url":"https://saucelabs.com/jobs/55191432e9e34666916c060197767811/video.flv","creation_time":1424850361,"custom-data":null,"browser_version":"6.1.","owner":"fcore","id":"55191432e9e34666916c060197767811","log_url":"https://saucelabs.com/jobs/55191432e9e34666916c060197767811/selenium-server.log","record_screenshots":true,"record_video":true,"build":"mobile-ecsearchv2","passed":true,"public":"public","status":"complete","tags":["false","f94aa90b3e05086fc8fba36c06297d02fb5267e9","mobile-ecsearchv2"],"start_time":1424850363,"proxied":true,"commands_not_successful":4,"name":"Browser tests for mobile-ecsearchv2","end_time":1424850412,"error":null,"os":"Mac 10.8","breakpointed":null,"browser":"ipad"},{"browser_short_version":"4.0","video_url":"https://saucelabs.com/jobs/77b70bdd57ff423ba45fb6629beae440/video.flv","creation_time":1424850361,"custom-data":null,"browser_version":"4.0.4.","owner":"fcore","id":"77b70bdd57ff423ba45fb6629beae440","log_url":"https://saucelabs.com/jobs/77b70bdd57ff423ba45fb6629beae440/selenium-server.log","record_screenshots":true,"record_video":true,"build":"mobile-ecsearchv2","passed":true,"public":"public","status":"complete","tags":["false","f94aa90b3e05086fc8fba36c06297d02fb5267e9","mobile-ecsearchv2"],"start_time":1424850363,"proxied":true,"commands_not_successful":2,"name":"Browser tests for mobile-ecsearchv2","end_time":1424850404,"error":null,"os":"Linux","breakpointed":null,"browser":"android"},{"browser_short_version":"7","video_url":"https://saucelabs.com/jobs/8a528801d9094e0abb3e0f5455f903bf/video.flv","creation_time":1424850361,"custom-data":null,"browser_version":"7.0.","owner":"fcore","id":"8a528801d9094e0abb3e0f5455f903bf","log_url":"https://saucelabs.com/jobs/8a528801d9094e0abb3e0f5455f903bf/selenium-server.log","record_screenshots":true,"record_video":true,"build":"mobile-ecsearchv2","passed":true,"public":"public","status":"complete","tags":["false","f94aa90b3e05086fc8fba36c06297d02fb5267e9","mobile-ecsearchv2"],"start_time":1424850363,"proxied":true,"commands_not_successful":3,"name":"Browser tests for mobile-ecsearchv2","end_time":1424850386,"error":null,"os":"Mac 10.9","breakpointed":null,"browser":"safari"},{"browser_short_version":"35","video_url":"https://saucelabs.com/jobs/a762e9ae7b464bea8c54c0619c6cf262/video.flv","creation_time":1424850361,"custom-data":null,"browser_version":"35.0.1916.153.","owner":"fcore","id":"a762e9ae7b464bea8c54c0619c6cf262","log_url":"https://saucelabs.com/jobs/a762e9ae7b464bea8c54c0619c6cf262/selenium-server.log","record_screenshots":true,"record_video":true,"build":"mobile-ecsearchv2","passed":true,"public":"public","status":"complete","tags":["false","f94aa90b3e05086fc8fba36c06297d02fb5267e9","mobile-ecsearchv2"],"start_time":1424850363,"proxied":true,"commands_not_successful":1,"name":"Browser tests for mobile-ecsearchv2","end_time":1424850380,"error":null,"os":"Linux","breakpointed":null,"browser":"googlechrome"},{"browser_short_version":"6.1","video_url":"https://saucelabs.com/jobs/ee41511fd2424f70b8cfee4669ef3783/video.flv","creation_time":1424850361,"custom-data":null,"browser_version":"6.1.","owner":"fcore","id":"ee41511fd2424f70b8cfee4669ef3783","log_url":"https://saucelabs.com/jobs/ee41511fd2424f70b8cfee4669ef3783/selenium-server.log","record_screenshots":true,"record_video":true,"build":"mobile-ecsearchv2","passed":true,"public":"public","status":"complete","tags":["false","f94aa90b3e05086fc8fba36c06297d02fb5267e9","mobile-ecsearchv2"],"start_time":1424850363,"proxied":true,"commands_not_successful":4,"name":"Browser tests for mobile-ecsearchv2","end_time":1424850409,"error":null,"os":"Mac 10.8","breakpointed":null,"browser":"iphone"},{"browser_short_version":"4.1","video_url":"https://saucelabs.com/jobs/ee9911af60744d0f94bebe53134f9599/video.flv","creation_time":1424850361,"custom-data":null,"browser_version":"4.1.","owner":"fcore","id":"ee9911af60744d0f94bebe53134f9599","log_url":"https://saucelabs.com/jobs/ee9911af60744d0f94bebe53134f9599/selenium-server.log","record_screenshots":true,"record_video":true,"build":"mobile-ecsearchv2","passed":true,"public":"public","status":"complete","tags":["false","f94aa90b3e05086fc8fba36c06297d02fb5267e9","mobile-ecsearchv2"],"start_time":1424850363,"proxied":true,"commands_not_successful":2,"name":"Browser tests for mobile-ecsearchv2","end_time":1424850406,"error":null,"os":"Linux","breakpointed":null,"browser":"android"},{"browser_short_version":"4.4","video_url":"https://saucelabs.com/jobs/fafdd5650b514703b6cb529b28d302d9/video.flv","creation_time":1424850361,"custom-data":null,"browser_version":"4.4.","owner":"fcore","id":"fafdd5650b514703b6cb529b28d302d9","log_url":"https://saucelabs.com/jobs/fafdd5650b514703b6cb529b28d302d9/selenium-server.log","record_screenshots":true,"record_video":true,"build":"mobile-ecsearchv2","passed":true,"public":"public","status":"complete","tags":["false","f94aa90b3e05086fc8fba36c06297d02fb5267e9","mobile-ecsearchv2"],"start_time":1424850363,"proxied":true,"commands_not_successful":2,"name":"Browser tests for mobile-ecsearchv2","end_time":1424850415,"error":null,"os":"Linux","breakpointed":null,"browser":"android"},{"browser_short_version":"4.0","video_url":"https://saucelabs.com/jobs/343d0b1d239b4a6e90470e508d00113e/video.flv","creation_time":1424850196,"custom-data":null,"browser_version":"4.0.4.","owner":"fcore","id":"343d0b1d239b4a6e90470e508d00113e","log_url":"https://saucelabs.com/jobs/343d0b1d239b4a6e90470e508d00113e/selenium-server.log","record_screenshots":true,"record_video":true,"build":"mobile-ecsearchv2","passed":true,"public":"public","status":"complete","tags":["216","f94aa90b3e05086fc8fba36c06297d02fb5267e9","mobile-ecsearchv2"],"start_time":1424850196,"proxied":true,"commands_not_successful":2,"name":"Browser tests for mobile-ecsearchv2","end_time":1424850240,"error":null,"os":"Linux","breakpointed":null,"browser":"android"},{"browser_short_version":"4.1","video_url":"https://saucelabs.com/jobs/80ae61722e504067a0f04d02ed6f5a2c/video.flv","creation_time":1424850196,"custom-data":null,"browser_version":"4.1.","owner":"fcore","id":"80ae61722e504067a0f04d02ed6f5a2c","log_url":"https://saucelabs.com/jobs/80ae61722e504067a0f04d02ed6f5a2c/selenium-server.log","record_screenshots":true,"record_video":true,"build":"mobile-ecsearchv2","passed":true,"public":"public","status":"complete","tags":["216","f94aa90b3e05086fc8fba36c06297d02fb5267e9","mobile-ecsearchv2"],"start_time":1424850196,"proxied":true,"commands_not_successful":2,"name":"Browser tests for mobile-ecsearchv2","end_time":1424850242,"error":null,"os":"Linux","breakpointed":null,"browser":"android"},{"browser_short_version":"6.1","video_url":"https://saucelabs.com/jobs/a4308ebd2f6d414981d915d7ca8c8209/video.flv","creation_time":1424850196,"custom-data":null,"browser_version":"6.1.","owner":"fcore","id":"a4308ebd2f6d414981d915d7ca8c8209","log_url":"https://saucelabs.com/jobs/a4308ebd2f6d414981d915d7ca8c8209/selenium-server.log","record_screenshots":true,"record_video":true,"build":"mobile-ecsearchv2","passed":true,"public":"public","status":"complete","tags":["216","f94aa90b3e05086fc8fba36c06297d02fb5267e9","mobile-ecsearchv2"],"start_time":1424850196,"proxied":true,"commands_not_successful":4,"name":"Browser tests for mobile-ecsearchv2","end_time":1424850244,"error":null,"os":"Mac 10.8","breakpointed":null,"browser":"iphone"},{"browser_short_version":"4.4","video_url":"https://saucelabs.com/jobs/0b24b000c43f48c48a8a2d01b3906726/video.flv","creation_time":1424850193,"custom-data":null,"browser_version":"4.4.","owner":"fcore","id":"0b24b000c43f48c48a8a2d01b3906726","log_url":"https://saucelabs.com/jobs/0b24b000c43f48c48a8a2d01b3906726/selenium-server.log","record_screenshots":true,"record_video":true,"build":"mobile-ecsearchv2","passed":true,"public":"public","status":"complete","tags":["216","f94aa90b3e05086fc8fba36c06297d02fb5267e9","mobile-ecsearchv2"],"start_time":1424850194,"proxied":true,"commands_not_successful":2,"name":"Browser tests for mobile-ecsearchv2","end_time":1424850244,"error":null,"os":"Linux","breakpointed":null,"browser":"android"},{"browser_short_version":"6.1","video_url":"https://saucelabs.com/jobs/2c30fa5e5c34405dbe11059df0dd574c/video.flv","creation_time":1424850193,"custom-data":null,"browser_version":"6.1.","owner":"fcore","id":"2c30fa5e5c34405dbe11059df0dd574c","log_url":"https://saucelabs.com/jobs/2c30fa5e5c34405dbe11059df0dd574c/selenium-server.log","record_screenshots":true,"record_video":true,"build":"mobile-ecsearchv2","passed":true,"public":"public","status":"complete","tags":["216","f94aa90b3e05086fc8fba36c06297d02fb5267e9","mobile-ecsearchv2"],"start_time":1424850194,"proxied":true,"commands_not_successful":4,"name":"Browser tests for mobile-ecsearchv2","end_time":1424850243,"error":null,"os":"Mac 10.8","breakpointed":null,"browser":"ipad"},{"browser_short_version":"35","video_url":"https://saucelabs.com/jobs/48185903e2bf4726b03499ad09feb950/video.flv","creation_time":1424850193,"custom-data":null,"browser_version":"35.0.1916.153.","owner":"fcore","id":"48185903e2bf4726b03499ad09feb950","log_url":"https://saucelabs.com/jobs/48185903e2bf4726b03499ad09feb950/selenium-server.log","record_screenshots":true,"record_video":true,"build":"mobile-ecsearchv2","passed":true,"public":"public","status":"complete","tags":["216","f94aa90b3e05086fc8fba36c06297d02fb5267e9","mobile-ecsearchv2"],"start_time":1424850194,"proxied":true,"commands_not_successful":1,"name":"Browser tests for mobile-ecsearchv2","end_time":1424850212,"error":null,"os":"Linux","breakpointed":null,"browser":"googlechrome"},{"browser_short_version":"7","video_url":"https://saucelabs.com/jobs/7a031f32ac3642a58d05ebffe88e5084/video.flv","creation_time":1424850193,"custom-data":null,"browser_version":"7.0.","owner":"fcore","id":"7a031f32ac3642a58d05ebffe88e5084","log_url":"https://saucelabs.com/jobs/7a031f32ac3642a58d05ebffe88e5084/selenium-server.log","record_screenshots":true,"record_video":true,"build":"mobile-ecsearchv2","passed":true,"public":"public","status":"complete","tags":["216","f94aa90b3e05086fc8fba36c06297d02fb5267e9","mobile-ecsearchv2"],"start_time":1424850194,"proxied":true,"commands_not_successful":3,"name":"Browser tests for mobile-ecsearchv2","end_time":1424850213,"error":null,"os":"Mac 10.9","breakpointed":null,"browser":"safari"},{"browser_short_version":"8.0","video_url":"https://saucelabs.com/jobs/333d0e397f4f4dc59ae4cd147d871089/video.flv","creation_time":1424850163,"custom-data":null,"browser_version":"8.0.","owner":"fcore","id":"333d0e397f4f4dc59ae4cd147d871089","log_url":"https://saucelabs.com/jobs/333d0e397f4f4dc59ae4cd147d871089/selenium-server.log","record_screenshots":true,"record_video":true,"build":"00-simple-single-page_52097945","passed":true,"public":"public","status":"complete","tags":["52097945","db19683075b734bc0c8f3c5bc16bd7e6b2c75594","fluxex"],"start_time":1424850164,"proxied":true,"commands_not_successful":7,"name":"FluxEx browser test for example: 00-simple-single-page_52097945","end_time":1424850391,"error":null,"os":"Mac 10.10","breakpointed":null,"browser":"ipad"},{"browser_short_version":"7.1","video_url":"https://saucelabs.com/jobs/40c8b314d6b34e8b9c39ae7280a6456f/video.flv","creation_time":1424850163,"custom-data":null,"browser_version":"7.1.","owner":"fcore","id":"40c8b314d6b34e8b9c39ae7280a6456f","log_url":"https://saucelabs.com/jobs/40c8b314d6b34e8b9c39ae7280a6456f/selenium-server.log","record_screenshots":true,"record_video":true,"build":"00-simple-single-page_52097945","passed":true,"public":"public","status":"complete","tags":["52097945","db19683075b734bc0c8f3c5bc16bd7e6b2c75594","fluxex"],"start_time":1424850164,"proxied":true,"commands_not_successful":7,"name":"FluxEx browser test for example: 00-simple-single-page_52097945","end_time":1424850259,"error":null,"os":"Mac 10.9","breakpointed":null,"browser":"ipad"},{"browser_short_version":"8.1","video_url":"https://saucelabs.com/jobs/a9695630b31c4c21b71ce0f70391cbea/video.flv","creation_time":1424850163,"custom-data":null,"browser_version":"8.1.","owner":"fcore","id":"a9695630b31c4c21b71ce0f70391cbea","log_url":"https://saucelabs.com/jobs/a9695630b31c4c21b71ce0f70391cbea/selenium-server.log","record_screenshots":true,"record_video":true,"build":"00-simple-single-page_52097945","passed":true,"public":"public","status":"complete","tags":["52097945","db19683075b734bc0c8f3c5bc16bd7e6b2c75594","fluxex"],"start_time":1424850164,"proxied":true,"commands_not_successful":7,"name":"FluxEx browser test for example: 00-simple-single-page_52097945","end_time":1424850305,"error":null,"os":"Mac 10.10","breakpointed":null,"browser":"ipad"},{"browser_short_version":"6.1","video_url":"https://saucelabs.com/jobs/df627330e3b1433ca6f86ed38b5da966/video.flv","creation_time":1424850163,"custom-data":null,"browser_version":"6.1.","owner":"fcore","id":"df627330e3b1433ca6f86ed38b5da966","log_url":"https://saucelabs.com/jobs/df627330e3b1433ca6f86ed38b5da966/selenium-server.log","record_screenshots":true,"record_video":true,"build":"00-simple-single-page_52097945","passed":true,"public":"public","status":"complete","tags":["52097945","db19683075b734bc0c8f3c5bc16bd7e6b2c75594","fluxex"],"start_time":1424850164,"proxied":true,"commands_not_successful":9,"name":"FluxEx browser test for example: 00-simple-single-page_52097945","end_time":1424850209,"error":null,"os":"Mac 10.8","breakpointed":null,"browser":"iphone"},{"browser_short_version":"4.4","video_url":"https://saucelabs.com/jobs/0848b96e727b48958f613d0844653c46/video.flv","creation_time":1424850162,"custom-data":null,"browser_version":"4.4.","owner":"fcore","id":"0848b96e727b48958f613d0844653c46","log_url":"https://saucelabs.com/jobs/0848b96e727b48958f613d0844653c46/selenium-server.log","record_screenshots":true,"record_video":true,"build":"00-simple-single-page_52097945","passed":true,"public":"public","status":"complete","tags":["52097945","db19683075b734bc0c8f3c5bc16bd7e6b2c75594","fluxex"],"start_time":1424850163,"proxied":true,"commands_not_successful":7,"name":"FluxEx browser test for example: 00-simple-single-page_52097945","end_time":1424850220,"error":null,"os":"Linux","breakpointed":null,"browser":"android"},{"browser_short_version":"8.1","video_url":"https://saucelabs.com/jobs/2f196728885e47268674d60615d5e458/video.flv","creation_time":1424850162,"custom-data":null,"browser_version":"8.1.","owner":"fcore","id":"2f196728885e47268674d60615d5e458","log_url":"https://saucelabs.com/jobs/2f196728885e47268674d60615d5e458/selenium-server.log","record_screenshots":true,"record_video":true,"build":"00-simple-single-page_52097945","passed":true,"public":"public","status":"complete","tags":["52097945","db19683075b734bc0c8f3c5bc16bd7e6b2c75594","fluxex"],"start_time":1424850163,"proxied":true,"commands_not_successful":7,"name":"FluxEx browser test for example: 00-simple-single-page_52097945","end_time":1424850244,"error":null,"os":"Mac 10.10","breakpointed":null,"browser":"iphone"},{"browser_short_version":"9","video_url":"https://saucelabs.com/jobs/408d57f2522a49f89a96b70adae94612/video.flv","creation_time":1424850162,"custom-data":null,"browser_version":"9.0.8112.16421.","owner":"fcore","id":"408d57f2522a49f89a96b70adae94612","log_url":"https://saucelabs.com/jobs/408d57f2522a49f89a96b70adae94612/selenium-server.log","record_screenshots":true,"record_video":true,"build":"00-simple-single-page_52097945","passed":true,"public":"public","status":"complete","tags":["52097945","db19683075b734bc0c8f3c5bc16bd7e6b2c75594","fluxex"],"start_time":1424850165,"proxied":true,"commands_not_successful":8,"name":"FluxEx browser test for example: 00-simple-single-page_52097945","end_time":1424850189,"error":null,"os":"Windows 2008","breakpointed":null,"browser":"iexplore"},{"browser_short_version":"7","video_url":"https://saucelabs.com/jobs/445eb967eb664d60930d65312995aec9/video.flv","creation_time":1424850162,"custom-data":null,"browser_version":"7.0.","owner":"fcore","id":"445eb967eb664d60930d65312995aec9","log_url":"https://saucelabs.com/jobs/445eb967eb664d60930d65312995aec9/selenium-server.log","record_screenshots":true,"record_video":true,"build":"00-simple-single-page_52097945","passed":true,"public":"public","status":"complete","tags":["52097945","db19683075b734bc0c8f3c5bc16bd7e6b2c75594","fluxex"],"start_time":1424850164,"proxied":true,"commands_not_successful":8,"name":"FluxEx browser test for example: 00-simple-single-page_52097945","end_time":1424850181,"error":null,"os":"Mac 10.9","breakpointed":null,"browser":"safari"},{"browser_short_version":"4.1","video_url":"https://saucelabs.com/jobs/6fbfe8cf58c44c149203cee1a048ad8b/video.flv","creation_time":1424850162,"custom-data":null,"browser_version":"4.1.","owner":"fcore","id":"6fbfe8cf58c44c149203cee1a048ad8b","log_url":"https://saucelabs.com/jobs/6fbfe8cf58c44c149203cee1a048ad8b/selenium-server.log","record_screenshots":true,"record_video":true,"build":"00-simple-single-page_52097945","passed":true,"public":"public","status":"complete","tags":["52097945","db19683075b734bc0c8f3c5bc16bd7e6b2c75594","fluxex"],"start_time":1424850164,"proxied":true,"commands_not_successful":7,"name":"FluxEx browser test for example: 00-simple-single-page_52097945","end_time":1424850216,"error":null,"os":"Linux","breakpointed":null,"browser":"android"},{"browser_short_version":"4.0","video_url":"https://saucelabs.com/jobs/71e39e56a65441458b288b0408af3724/video.flv","creation_time":1424850162,"custom-data":null,"browser_version":"4.0.4.","owner":"fcore","id":"71e39e56a65441458b288b0408af3724","log_url":"https://saucelabs.com/jobs/71e39e56a65441458b288b0408af3724/selenium-server.log","record_screenshots":true,"record_video":true,"build":"00-simple-single-page_52097945","passed":true,"public":"public","status":"complete","tags":["52097945","db19683075b734bc0c8f3c5bc16bd7e6b2c75594","fluxex"],"start_time":1424850164,"proxied":true,"commands_not_successful":7,"name":"FluxEx browser test for example: 00-simple-single-page_52097945","end_time":1424850221,"error":null,"os":"Linux","breakpointed":null,"browser":"android"},{"browser_short_version":"11","video_url":"https://saucelabs.com/jobs/8ea10343cb74407a8fc444f7769b8bfb/video.flv","creation_time":1424850162,"custom-data":null,"browser_version":"11.0.9600.17278.","owner":"fcore","id":"8ea10343cb74407a8fc444f7769b8bfb","log_url":"https://saucelabs.com/jobs/8ea10343cb74407a8fc444f7769b8bfb/selenium-server.log","record_screenshots":true,"record_video":true,"build":"00-simple-single-page_52097945","passed":true,"public":"public","status":"complete","tags":["52097945","db19683075b734bc0c8f3c5bc16bd7e6b2c75594","fluxex"],"start_time":1424850164,"proxied":true,"commands_not_successful":8,"name":"FluxEx browser test for example: 00-simple-single-page_52097945","end_time":1424850181,"error":null,"os":"Windows 2012 R2","breakpointed":null,"browser":"iexplore"},{"browser_short_version":"8.0","video_url":"https://saucelabs.com/jobs/9bf1c6e330084e71b499bccc6ef38adc/video.flv","creation_time":1424850162,"custom-data":null,"browser_version":"8.0.","owner":"fcore","id":"9bf1c6e330084e71b499bccc6ef38adc","log_url":"https://saucelabs.com/jobs/9bf1c6e330084e71b499bccc6ef38adc/selenium-server.log","record_screenshots":true,"record_video":true,"build":"00-simple-single-page_52097945","passed":true,"public":"public","status":"complete","tags":["52097945","db19683075b734bc0c8f3c5bc16bd7e6b2c75594","fluxex"],"start_time":1424850164,"proxied":true,"commands_not_successful":7,"name":"FluxEx browser test for example: 00-simple-single-page_52097945","end_time":1424850266,"error":null,"os":"Mac 10.10","breakpointed":null,"browser":"iphone"},{"browser_short_version":"7.1","video_url":"https://saucelabs.com/jobs/9d8723766e8c4cb8a9e7b9b51206bec7/video.flv","creation_time":1424850162,"custom-data":null,"browser_version":"7.1.","owner":"fcore","id":"9d8723766e8c4cb8a9e7b9b51206bec7","log_url":"https://saucelabs.com/jobs/9d8723766e8c4cb8a9e7b9b51206bec7/selenium-server.log","record_screenshots":true,"record_video":true,"build":"00-simple-single-page_52097945","passed":true,"public":"public","status":"complete","tags":["52097945","db19683075b734bc0c8f3c5bc16bd7e6b2c75594","fluxex"],"start_time":1424850163,"proxied":true,"commands_not_successful":7,"name":"FluxEx browser test for example: 00-simple-single-page_52097945","end_time":1424850270,"error":null,"os":"Mac 10.9","breakpointed":null,"browser":"iphone"},{"browser_short_version":"6.1","video_url":"https://saucelabs.com/jobs/c7854ed481a048649cda183f4722db93/video.flv","creation_time":1424850162,"custom-data":null,"browser_version":"6.1.","owner":"fcore","id":"c7854ed481a048649cda183f4722db93","log_url":"https://saucelabs.com/jobs/c7854ed481a048649cda183f4722db93/selenium-server.log","record_screenshots":true,"record_video":true,"build":"00-simple-single-page_52097945","passed":true,"public":"public","status":"complete","tags":["52097945","db19683075b734bc0c8f3c5bc16bd7e6b2c75594","fluxex"],"start_time":1424850163,"proxied":true,"commands_not_successful":9,"name":"FluxEx browser test for example: 00-simple-single-page_52097945","end_time":1424850214,"error":null,"os":"Mac 10.8","breakpointed":null,"browser":"ipad"},{"browser_short_version":"35","video_url":"https://saucelabs.com/jobs/cca5871f93d14664bff229edec781f6a/video.flv","creation_time":1424850162,"custom-data":null,"browser_version":"35.0.1916.153.","owner":"fcore","id":"cca5871f93d14664bff229edec781f6a","log_url":"https://saucelabs.com/jobs/cca5871f93d14664bff229edec781f6a/selenium-server.log","record_screenshots":true,"record_video":true,"build":"00-simple-single-page_52097945","passed":true,"public":"public","status":"complete","tags":["52097945","db19683075b734bc0c8f3c5bc16bd7e6b2c75594","fluxex"],"start_time":1424850163,"proxied":true,"commands_not_successful":3,"name":"FluxEx browser test for example: 00-simple-single-page_52097945","end_time":1424850181,"error":null,"os":"Linux","breakpointed":null,"browser":"googlechrome"},{"browser_short_version":"34","video_url":"https://saucelabs.com/jobs/d009ee43077b4fff9864f5a0b060cd21/video.flv","creation_time":1424850162,"custom-data":null,"browser_version":"34.0.","owner":"fcore","id":"d009ee43077b4fff9864f5a0b060cd21","log_url":"https://saucelabs.com/jobs/d009ee43077b4fff9864f5a0b060cd21/selenium-server.log","record_screenshots":true,"record_video":true,"build":"00-simple-single-page_52097945","passed":true,"public":"public","status":"complete","tags":["52097945","db19683075b734bc0c8f3c5bc16bd7e6b2c75594","fluxex"],"start_time":1424850163,"proxied":true,"commands_not_successful":3,"name":"FluxEx browser test for example: 00-simple-single-page_52097945","end_time":1424850184,"error":null,"os":"Linux","breakpointed":null,"browser":"firefox"},{"browser_short_version":"6","video_url":"https://saucelabs.com/jobs/d47d0c48b5b642548df6ac30a289004b/video.flv","creation_time":1424850162,"custom-data":null,"browser_version":"6.0.4.","owner":"fcore","id":"d47d0c48b5b642548df6ac30a289004b","log_url":"https://saucelabs.com/jobs/d47d0c48b5b642548df6ac30a289004b/selenium-server.log","record_screenshots":true,"record_video":true,"build":"00-simple-single-page_52097945","passed":true,"public":"public","status":"complete","tags":["52097945","db19683075b734bc0c8f3c5bc16bd7e6b2c75594","fluxex"],"start_time":1424850163,"proxied":true,"commands_not_successful":8,"name":"FluxEx browser test for example: 00-simple-single-page_52097945","end_time":1424850181,"error":null,"os":"Mac 10.8","breakpointed":null,"browser":"safari"},{"browser_short_version":"10","video_url":"https://saucelabs.com/jobs/de47d340b6fd415883afff3d03b1d713/video.flv","creation_time":1424850162,"custom-data":null,"browser_version":"10.0.9200.16580.","owner":"fcore","id":"de47d340b6fd415883afff3d03b1d713","log_url":"https://saucelabs.com/jobs/de47d340b6fd415883afff3d03b1d713/selenium-server.log","record_screenshots":true,"record_video":true,"build":"00-simple-single-page_52097945","passed":true,"public":"public","status":"complete","tags":["52097945","db19683075b734bc0c8f3c5bc16bd7e6b2c75594","fluxex"],"start_time":1424850164,"proxied":true,"commands_not_successful":8,"name":"FluxEx browser test for example: 00-simple-single-page_52097945","end_time":1424850186,"error":null,"os":"Windows 2012","breakpointed":null,"browser":"iexplore"},{"browser_short_version":"8.1","video_url":"https://saucelabs.com/jobs/0e70b47ebddb484a860a4fded3736309/video.flv","creation_time":1424849910,"custom-data":null,"browser_version":"8.1.","owner":"fcore","id":"0e70b47ebddb484a860a4fded3736309","log_url":"https://saucelabs.com/jobs/0e70b47ebddb484a860a4fded3736309/selenium-server.log","record_screenshots":true,"record_video":true,"build":"00hello_52097216","passed":true,"public":"public","status":"complete","tags":["52097216","5bdfd8da7720e8939a75e0fc31f434d877bc6489","fluxex"],"start_time":1424849910,"proxied":true,"commands_not_successful":7,"name":"FluxEx browser test for example: 00hello_52097216","end_time":1424849993,"error":null,"os":"Mac 10.10","breakpointed":null,"browser":"iphone"},{"browser_short_version":"6","video_url":"https://saucelabs.com/jobs/013e3eeb14954683a63d4d3bfa507662/video.flv","creation_time":1424849550,"custom-data":null,"browser_version":"6.0.4.","owner":"fcore","id":"013e3eeb14954683a63d4d3bfa507662","log_url":"https://saucelabs.com/jobs/013e3eeb14954683a63d4d3bfa507662/selenium-server.log","record_screenshots":true,"record_video":true,"build":"00hello_52097216","passed":true,"public":"public","status":"complete","tags":["52097216","5bdfd8da7720e8939a75e0fc31f434d877bc6489","fluxex"],"start_time":1424849552,"proxied":true,"commands_not_successful":8,"name":"FluxEx browser test for example: 00hello_52097216","end_time":1424849569,"error":null,"os":"Mac 10.8","breakpointed":null,"browser":"safari"},{"browser_short_version":"34","video_url":"https://saucelabs.com/jobs/1571679a0d8d4bcfb30c768c5e06aa28/video.flv","creation_time":1424849550,"custom-data":null,"browser_version":"34.0.","owner":"fcore","id":"1571679a0d8d4bcfb30c768c5e06aa28","log_url":"https://saucelabs.com/jobs/1571679a0d8d4bcfb30c768c5e06aa28/selenium-server.log","record_screenshots":true,"record_video":true,"build":"00hello_52097216","passed":true,"public":"public","status":"complete","tags":["52097216","5bdfd8da7720e8939a75e0fc31f434d877bc6489","fluxex"],"start_time":1424849551,"proxied":true,"commands_not_successful":3,"name":"FluxEx browser test for example: 00hello_52097216","end_time":1424849572,"error":null,"os":"Linux","breakpointed":null,"browser":"firefox"},{"browser_short_version":"4.1","video_url":"https://saucelabs.com/jobs/353e018d4eec4464b59c5c0b4ea3ec5d/video.flv","creation_time":1424849550,"custom-data":null,"browser_version":"4.1.","owner":"fcore","id":"353e018d4eec4464b59c5c0b4ea3ec5d","log_url":"https://saucelabs.com/jobs/353e018d4eec4464b59c5c0b4ea3ec5d/selenium-server.log","record_screenshots":true,"record_video":true,"build":"00hello_52097216","passed":true,"public":"public","status":"complete","tags":["52097216","5bdfd8da7720e8939a75e0fc31f434d877bc6489","fluxex"],"start_time":1424849552,"proxied":true,"commands_not_successful":7,"name":"FluxEx browser test for example: 00hello_52097216","end_time":1424849614,"error":null,"os":"Linux","breakpointed":null,"browser":"android"},{"browser_short_version":"10","video_url":"https://saucelabs.com/jobs/36fe90fc9dad42559ce010344cb79540/video.flv","creation_time":1424849550,"custom-data":null,"browser_version":"10.0.9200.16580.","owner":"fcore","id":"36fe90fc9dad42559ce010344cb79540","log_url":"https://saucelabs.com/jobs/36fe90fc9dad42559ce010344cb79540/selenium-server.log","record_screenshots":true,"record_video":true,"build":"00hello_52097216","passed":true,"public":"public","status":"complete","tags":["52097216","5bdfd8da7720e8939a75e0fc31f434d877bc6489","fluxex"],"start_time":1424849552,"proxied":true,"commands_not_successful":8,"name":"FluxEx browser test for example: 00hello_52097216","end_time":1424849571,"error":null,"os":"Windows 2012","breakpointed":null,"browser":"iexplore"},{"browser_short_version":"8.0","video_url":"https://saucelabs.com/jobs/3758c6e3a8684af9bc1e2e42d48ca42f/video.flv","creation_time":1424849550,"custom-data":null,"browser_version":"8.0.","owner":"fcore","id":"3758c6e3a8684af9bc1e2e42d48ca42f","log_url":"https://saucelabs.com/jobs/3758c6e3a8684af9bc1e2e42d48ca42f/selenium-server.log","record_screenshots":true,"record_video":true,"build":"00hello_52097216","passed":true,"public":"public","status":"complete","tags":["52097216","5bdfd8da7720e8939a75e0fc31f434d877bc6489","fluxex"],"start_time":1424849552,"proxied":true,"commands_not_successful":7,"name":"FluxEx browser test for example: 00hello_52097216","end_time":1424849645,"error":null,"os":"Mac 10.10","breakpointed":null,"browser":"iphone"},{"browser_short_version":"6.1","video_url":"https://saucelabs.com/jobs/44a0e9266fec4b15a61a1e8b6c0d22ce/video.flv","creation_time":1424849550,"custom-data":null,"browser_version":"6.1.","owner":"fcore","id":"44a0e9266fec4b15a61a1e8b6c0d22ce","log_url":"https://saucelabs.com/jobs/44a0e9266fec4b15a61a1e8b6c0d22ce/selenium-server.log","record_screenshots":true,"record_video":true,"build":"00hello_52097216","passed":true,"public":"public","status":"complete","tags":["52097216","5bdfd8da7720e8939a75e0fc31f434d877bc6489","fluxex"],"start_time":1424849552,"proxied":true,"commands_not_successful":9,"name":"FluxEx browser test for example: 00hello_52097216","end_time":1424849614,"error":null,"os":"Mac 10.8","breakpointed":null,"browser":"iphone"},{"browser_short_version":"4.0","video_url":"https://saucelabs.com/jobs/4c27138353064eb2bdd8d0c5d1b0eba1/video.flv","creation_time":1424849550,"custom-data":null,"browser_version":"4.0.4.","owner":"fcore","id":"4c27138353064eb2bdd8d0c5d1b0eba1","log_url":"https://saucelabs.com/jobs/4c27138353064eb2bdd8d0c5d1b0eba1/selenium-server.log","record_screenshots":true,"record_video":true,"build":"00hello_52097216","passed":true,"public":"public","status":"complete","tags":["52097216","5bdfd8da7720e8939a75e0fc31f434d877bc6489","fluxex"],"start_time":1424849551,"proxied":true,"commands_not_successful":7,"name":"FluxEx browser test for example: 00hello_52097216","end_time":1424849615,"error":null,"os":"Linux","breakpointed":null,"browser":"android"},{"browser_short_version":"9","video_url":"https://saucelabs.com/jobs/4f49d236be424ef9a4508bbc2d42346a/video.flv","creation_time":1424849550,"custom-data":null,"browser_version":"9.0.8112.16421.","owner":"fcore","id":"4f49d236be424ef9a4508bbc2d42346a","log_url":"https://saucelabs.com/jobs/4f49d236be424ef9a4508bbc2d42346a/selenium-server.log","record_screenshots":true,"record_video":true,"build":"00hello_52097216","passed":true,"public":"public","status":"complete","tags":["52097216","5bdfd8da7720e8939a75e0fc31f434d877bc6489","fluxex"],"start_time":1424849552,"proxied":true,"commands_not_successful":8,"name":"FluxEx browser test for example: 00hello_52097216","end_time":1424849577,"error":null,"os":"Windows 2008","breakpointed":null,"browser":"iexplore"},{"browser_short_version":"35","video_url":"https://saucelabs.com/jobs/52bd71d97faf425da0e75a26ff7b962f/video.flv","creation_time":1424849550,"custom-data":null,"browser_version":"35.0.1916.153.","owner":"fcore","id":"52bd71d97faf425da0e75a26ff7b962f","log_url":"https://saucelabs.com/jobs/52bd71d97faf425da0e75a26ff7b962f/selenium-server.log","record_screenshots":true,"record_video":true,"build":"00hello_52097216","passed":true,"public":"public","status":"complete","tags":["52097216","5bdfd8da7720e8939a75e0fc31f434d877bc6489","fluxex"],"start_time":1424849550,"proxied":true,"commands_not_successful":3,"name":"FluxEx browser test for example: 00hello_52097216","end_time":1424849569,"error":null,"os":"Linux","breakpointed":null,"browser":"googlechrome"},{"browser_short_version":"4.4","video_url":"https://saucelabs.com/jobs/57ba10b991df444ebe986bb9307357c9/video.flv","creation_time":1424849550,"custom-data":null,"browser_version":"4.4.","owner":"fcore","id":"57ba10b991df444ebe986bb9307357c9","log_url":"https://saucelabs.com/jobs/57ba10b991df444ebe986bb9307357c9/selenium-server.log","record_screenshots":true,"record_video":true,"build":"00hello_52097216","passed":true,"public":"public","status":"complete","tags":["52097216","5bdfd8da7720e8939a75e0fc31f434d877bc6489","fluxex"],"start_time":1424849552,"proxied":true,"commands_not_successful":7,"name":"FluxEx browser test for example: 00hello_52097216","end_time":1424849624,"error":null,"os":"Linux","breakpointed":null,"browser":"android"},{"browser_short_version":"7.1","video_url":"https://saucelabs.com/jobs/8cebab52f1bc4fd8b269e295fcd427b2/video.flv","creation_time":1424849550,"custom-data":null,"browser_version":"7.1.","owner":"fcore","id":"8cebab52f1bc4fd8b269e295fcd427b2","log_url":"https://saucelabs.com/jobs/8cebab52f1bc4fd8b269e295fcd427b2/selenium-server.log","record_screenshots":true,"record_video":true,"build":"00hello_52097216","passed":true,"public":"public","status":"complete","tags":["52097216","5bdfd8da7720e8939a75e0fc31f434d877bc6489","fluxex"],"start_time":1424849552,"proxied":true,"commands_not_successful":7,"name":"FluxEx browser test for example: 00hello_52097216","end_time":1424849618,"error":null,"os":"Mac 10.9","breakpointed":null,"browser":"ipad"},{"browser_short_version":"8.0","video_url":"https://saucelabs.com/jobs/9edd902b909b41c2a98ee5391c839f46/video.flv","creation_time":1424849550,"custom-data":null,"browser_version":"8.0.","owner":"fcore","id":"9edd902b909b41c2a98ee5391c839f46","log_url":"https://saucelabs.com/jobs/9edd902b909b41c2a98ee5391c839f46/selenium-server.log","record_screenshots":true,"record_video":true,"build":"00hello_52097216","passed":true,"public":"public","status":"complete","tags":["52097216","5bdfd8da7720e8939a75e0fc31f434d877bc6489","fluxex"],"start_time":1424849552,"proxied":true,"commands_not_successful":7,"name":"FluxEx browser test for example: 00hello_52097216","end_time":1424849654,"error":null,"os":"Mac 10.10","breakpointed":null,"browser":"ipad"},{"browser_short_version":"11","video_url":"https://saucelabs.com/jobs/9f8cd1607bb54253bd26283bdc9cadb6/video.flv","creation_time":1424849550,"custom-data":null,"browser_version":"11.0.9600.17278.","owner":"fcore","id":"9f8cd1607bb54253bd26283bdc9cadb6","log_url":"https://saucelabs.com/jobs/9f8cd1607bb54253bd26283bdc9cadb6/selenium-server.log","record_screenshots":true,"record_video":true,"build":"00hello_52097216","passed":true,"public":"public","status":"complete","tags":["52097216","5bdfd8da7720e8939a75e0fc31f434d877bc6489","fluxex"],"start_time":1424849551,"proxied":true,"commands_not_successful":8,"name":"FluxEx browser test for example: 00hello_52097216","end_time":1424849572,"error":null,"os":"Windows 2012 R2","breakpointed":null,"browser":"iexplore"}]}
